{
"server":"ia600605.us.archive.org",
"dir":"/35/items/here_takemyheart_1208_librivox",
"metadata":{"collection":["librivoxaudio","audio_bookspoetry","opensource_audio"],"mediatype":["audio"],"title":["Here, Take My Heart"],"creator":["Thomas Moore"],"taper":["LibriVox"],"source":["Librivox recording of a public-domain text"],"identifier":["here_takemyheart_1208_librivox"],"addeddate":["2012-08-06 00:30:41"],"publicdate":["2012-08-06 00:37:18"],"description":["<a href=\"http:\/\/librivox.org\/\" rel=\"nofollow\">LibriVox<\/a> volunteers bring you 23 recordings of Here, Take My Heart by Thomas Moore. \nThis was the Weekly Poetry project for July 29, 2012.\n\nThis weekly poem is one of the many love poems by the 19th-century irish poem Thomas Moore. Some of his poems were composed. One of his best known poems is The Last Rose Of Summer. This weekly poem will be closed on sunday 5 August 2012.\" (Summary by Stav Nisser)\n\nFor further information, including links to online text, reader information, RSS feeds, CD cover or other formats (if available), please go to the <a href=\"http:\/\/librivox.org\/here-take-my-heart-by-thomas-moore\/\" rel=\"nofollow\">LibriVox catalog page<\/a> for this recording. \n\nFor more free audio books or to become a volunteer reader, visit <a href=\"http:\/\/librivox.org\/\" rel=\"nofollow\">LibriVox.org<\/a>.\n\n<a href=\"http:\/\/archive.org\/download\/LibrivoxM4bCollectionAudiobooks_13\/HereTakeMyHeart.m4b\" rel=\"nofollow\">Download M4B (15MB)<\/a><br \/>"],"date":["2012-08-05"],"year":["2012"],"subject":["librivox; literature; audiobook; poetry; romance"],"licenseurl":["http:\/\/creativecommons.org\/publicdomain\/mark\/1.0\/"],"curation":["[curator]malware@archive.org[\/curator][date]20140324104615[\/date][comment]checked for malware[\/comment]"],"boxid":["OL100020508"]},
"files":
{"\/Here_Take_Heart_1209.jpg":{"source":"original","format":"JPEG","mtime":"1401914943","size":"129518","md5":"57f8225e6e15a439dc3cfdd833d23734","crc32":"5d5318f5","sha1":"849f28d44d6b63eb67033305c923ad52d76f42d7"},"\/Here_Take_Heart_1209_thumb.jpg":{"source":"derivative","format":"JPEG Thumb","original":"Here_Take_Heart_1209.jpg","mtime":"1414068520","size":"8375","md5":"743a73814d3445e253575e753acc7464","crc32":"4516f860","sha1":"4bde1b8e8ab28676bb29a19abe864aa08563cc08"},"\/here_takemyheart_1208_librivox_archive.torrent":{"source":"original","btih":"ab33e82f71dfcc29694426e7f1d85dcea6d649fb","mtime":"1414325959","size":"21370","md5":"4bf6f71e1bb516fabb6096e55e89597c","crc32":"9204146d","sha1":"e033e254ab2d11b4b9b61bb4c28626d36d5ba59f","format":"Archive BitTorrent"},"\/here_takemyheart_1208_librivox_files.xml":{"source":"original","format":"Metadata","md5":"dc9ab289790326049e669c911fad8fe1"},"\/here_takemyheart_1208_librivox_meta.xml":{"source":"original","format":"Metadata","mtime":"1414325957","size":"2004","md5":"d0fa76274ad57162cffbc9f5315ae379","crc32":"0039bc96","sha1":"9b9c8b87a2c571dfa8ef92fca3ee8ebcb3d42b78"},"\/heretakemyheart_moore_ag.mp3":{"source":"original","format":"128Kbps MP3","creator":"Thomas Moore","album":"LibriVox Weekly Poetry","title":"Here, Take My Heart - Read by AG","length":"83.59","mtime":"1344213019","size":"1339520","md5":"7bef51bd6c844e71801d63cee7c3b24b","crc32":"781b0e53","sha1":"e078795fe00bcd6347d3c16deabb7358db462e84","artist":"Thomas Moore","genre":"Speech","track":"1","external-identifier":"urn:acoustid:unknown","height":"0","width":"0"},"\/heretakemyheart_moore_ag.ogg":{"source":"derivative","format":"Ogg Vorbis","original":"heretakemyheart_moore_ag.mp3","mtime":"1344213412","size":"779417","md5":"eeeccd53ca5e2eb2fe094e3c6966fe91","crc32":"24b26fc5","sha1":"87ddb043c15ae674aed1fbaf8f3d0843f5ace076","length":"78.69","height":"0","width":"0"},"\/heretakemyheart_moore_ag.png":{"source":"derivative","format":"PNG","original":"heretakemyheart_moore_ag.ogg","mtime":"1414068592","size":"10431","md5":"d2194246fc7a82453e32cefbfe1412b4","crc32":"5b40fe82","sha1":"7d23cf1c3a5cacb6f16a78c53b5abe29ad7317e1"},"\/heretakemyheart_moore_ag_64kb.mp3":{"source":"derivative","creator":"Thomas Moore","title":"Here, Take My Heart - Read by AG","track":"1","album":"LibriVox Weekly Poetry","genre":"Speech","bitrate":"64","length":"01:23","format":"64Kbps MP3","original":"heretakemyheart_moore_ag.mp3","mtime":"1414068467","size":"778752","md5":"5943dedc4c89ba3bde26b2817a97b3d3","crc32":"23521515","sha1":"b53c1224dd86d97874a116efa7d7fce979903a00","height":"0","width":"0"},"\/heretakemyheart_moore_alp.mp3":{"source":"original","format":"128Kbps MP3","creator":"Thomas Moore","album":"LibriVox Weekly Poetry","title":"Here, Take My Heart - Read by ALP","length":"76.04","mtime":"1344213016","size":"1218560","md5":"860239f388c3af063b6befcde6d1742c","crc32":"f41873a0","sha1":"86df3115d47dd3b13a3158e91d2fc6d78867ea3b","artist":"Thomas Moore","genre":"Speech","track":"2","external-identifier":"urn:acoustid:unknown","height":"0","width":"0"},"\/heretakemyheart_moore_alp.ogg":{"source":"derivative","format":"Ogg Vorbis","original":"heretakemyheart_moore_alp.mp3","mtime":"1344213373","size":"688438","md5":"aaeecf763ecdcbf1e266aeb240a1de0e","crc32":"0e7e6bd0","sha1":"753fe500a61a8188bd5ca4b50708422fce0a051b","length":"71.31","height":"0","width":"0"},"\/heretakemyheart_moore_alp.png":{"source":"derivative","format":"PNG","original":"heretakemyheart_moore_alp.ogg","mtime":"1414068584","size":"11161","md5":"45c9f389036b96dc9a2be64ff62d013a","crc32":"72dc4310","sha1":"858bdfdd8585a4babbe125798b337dda3620c9c3"},"\/heretakemyheart_moore_alp_64kb.mp3":{"source":"derivative","creator":"Thomas Moore","title":"Here, Take My Heart - Read by ALP","track":"2","album":"LibriVox Weekly Poetry","genre":"Speech","bitrate":"64","length":"01:16","format":"64Kbps MP3","original":"heretakemyheart_moore_alp.mp3","mtime":"1414068463","size":"718336","md5":"fb7dff3d5554cdd1078005dbfbf34ef8","crc32":"780ece0e","sha1":"056cf26bd704765263fdb8e390f3f7fdcfc330a3","height":"0","width":"0"},"\/heretakemyheart_moore_bee.mp3":{"source":"original","format":"128Kbps MP3","creator":"Thomas Moore","album":"LibriVox Weekly Poetry","title":"Here, Take My Heart - Read by BEE","length":"77.06","mtime":"1344213024","size":"1235118","md5":"44539db55cd052f7aed5d2b52f12a1da","crc32":"f3db846b","sha1":"cc1dd35eb0bf2d3fccc6c3cace107bb2f070d44d","artist":"Thomas Moore","genre":"Speech","track":"3","external-identifier":"urn:acoustid:unknown","height":"0","width":"0"},"\/heretakemyheart_moore_bee.ogg":{"source":"derivative","format":"Ogg Vorbis","original":"heretakemyheart_moore_bee.mp3","mtime":"1344213350","size":"690395","md5":"a0c6c3f919f5bad76e37ad7901d833f8","crc32":"16437474","sha1":"f64fc0ef3b9d781afb9bb9e897badf163cae9da2","length":"72.79","height":"0","width":"0"},"\/heretakemyheart_moore_bee.png":{"source":"derivative","format":"PNG","original":"heretakemyheart_moore_bee.ogg","mtime":"1414068567","size":"11574","md5":"6688d670991709dade58afc7d7cbb1f8","crc32":"bb72912e","sha1":"511e16f8a6bcc0c43aead2292aae51863dd7b527"},"\/heretakemyheart_moore_bee_64kb.mp3":{"source":"derivative","creator":"Thomas Moore","title":"Here, Take My Heart - Read by BEE","track":"3","album":"LibriVox Weekly Poetry","genre":"Speech","bitrate":"64","length":"01:17","format":"64Kbps MP3","original":"heretakemyheart_moore_bee.mp3","mtime":"1414068471","size":"726528","md5":"6f4d797ba0d87e139f54f398c9066df7","crc32":"9994a3d6","sha1":"6ed9aef25aa95431779f698068f3a6dcc49c4e58","height":"0","width":"0"},"\/heretakemyheart_moore_cam.mp3":{"source":"original","format":"128Kbps MP3","creator":"Thomas Moore","album":"LibriVox Weekly Poetry","title":"Here, Take My Heart - Read by CAM","length":"92.99","mtime":"1344213004","size":"1489198","md5":"bcdfb13a97df9661d2c2d67965d6d164","crc32":"84616458","sha1":"9a9b2f93e735c539a1fda52981d9af8964545c2a","artist":"Thomas Moore","genre":"Speech","track":"4","external-identifier":"urn:acoustid:unknown","height":"0","width":"0"},"\/heretakemyheart_moore_cam.ogg":{"source":"derivative","format":"Ogg Vorbis","original":"heretakemyheart_moore_cam.mp3","mtime":"1344213325","size":"851367","md5":"de14328b8d6c8bc403ac7a1279eee584","crc32":"caeb21b3","sha1":"532bbdc800c33eda890a6f24acd4140d362c721c","length":"88.28","height":"0","width":"0"},"\/heretakemyheart_moore_cam.png":{"source":"derivative","format":"PNG","original":"heretakemyheart_moore_cam.ogg","mtime":"1414068581","size":"10864","md5":"cb09d18396a9dd940d024e42614be115","crc32":"3b8f0ba3","sha1":"9fe45a0ecb45f856570d9009da4a427c0d7e2ba6"},"\/heretakemyheart_moore_cam_64kb.mp3":{"source":"derivative","creator":"Thomas Moore","title":"Here, Take My Heart - Read by CAM","track":"4","album":"LibriVox Weekly Poetry","genre":"Speech","bitrate":"64","length":"01:33","format":"64Kbps MP3","original":"heretakemyheart_moore_cam.mp3","mtime":"1414068435","size":"854016","md5":"3d46c55e84483c9ff29155b5086b50f3","crc32":"78b3cb3e","sha1":"08a12c75a5fbca9d6f90658fabdd305aa2f5ab61","height":"0","width":"0"},"\/heretakemyheart_moore_cc.mp3":{"source":"original","format":"128Kbps MP3","creator":"Thomas Moore","album":"LibriVox Weekly Poetry","title":"Here, Take My Heart - Read by CC","length":"82.49","mtime":"1344213033","size":"1321134","md5":"4ceaea4b00fd18e4585acc4058a8eb05","crc32":"b3f90c0d","sha1":"c2a12685a406974b46ca91bc7ea0935778ec43e3","artist":"Thomas Moore","genre":"Speech","track":"5","external-identifier":"urn:acoustid:unknown","height":"0","width":"0"},"\/heretakemyheart_moore_cc.ogg":{"source":"derivative","format":"Ogg Vorbis","original":"heretakemyheart_moore_cc.mp3","mtime":"1344213257","size":"748904","md5":"aab7a3afcac6ab708f727be62b9abe77","crc32":"5044de05","sha1":"e84490920acac79c39a43f617e80d7473329d3d5","length":"78.98","height":"0","width":"0"},"\/heretakemyheart_moore_cc.png":{"source":"derivative","format":"PNG","original":"heretakemyheart_moore_cc.ogg","mtime":"1414068540","size":"10264","md5":"abfdd1e116d8fb5f3be11296905d498b","crc32":"cc14370a","sha1":"bda8674352cc133d3780f2552818833a6e2152c9"},"\/heretakemyheart_moore_cc_64kb.mp3":{"source":"derivative","creator":"Thomas Moore","title":"Here, Take My Heart - Read by CC","track":"5","album":"LibriVox Weekly Poetry","genre":"Speech","bitrate":"64","length":"01:22","format":"64Kbps MP3","original":"heretakemyheart_moore_cc.mp3","mtime":"1414068479","size":"770048","md5":"ed251450f127e5cf3e22d935435ddf26","crc32":"960996f6","sha1":"191ef94daa305571fd79bda0240b484df5704783","height":"0","width":"0"},"\/heretakemyheart_moore_cmp.mp3":{"source":"original","format":"128Kbps MP3","creator":"Thomas Moore","album":"LibriVox Weekly Poetry","title":"Here, Take My Heart - Read by CMP","length":"98.89","mtime":"1344213036","size":"1585152","md5":"737a7ad2cda1468a015499bde56d2dda","crc32":"a2f492cf","sha1":"90b3fa7c50c102263018e408474247a38fc2ee48","artist":"Thomas Moore","genre":"Speech","track":"6","external-identifier":"urn:acoustid:unknown","height":"0","width":"0"},"\/heretakemyheart_moore_cmp.ogg":{"source":"derivative","format":"Ogg Vorbis","original":"heretakemyheart_moore_cmp.mp3","mtime":"1344213274","size":"883978","md5":"099b05ce3ba2a1554e2c4f3eae2c1b9e","crc32":"a4f18bf1","sha1":"d9f9176950bf4303fed579f02e489e8b4dbb4741","length":"94","height":"0","width":"0"},"\/heretakemyheart_moore_cmp.png":{"source":"derivative","format":"PNG","original":"heretakemyheart_moore_cmp.ogg","mtime":"1414068595","size":"10376","md5":"b04a9d74ef376d99e35e8ed7bcbf3903","crc32":"921f376d","sha1":"1a528e7ccc7a3add874ba9be789f43fb19eaf657"},"\/heretakemyheart_moore_cmp_64kb.mp3":{"source":"derivative","creator":"Thomas Moore","title":"Here, Take My Heart - Read by CMP","track":"6","album":"LibriVox Weekly Poetry","genre":"Speech","bitrate":"64","length":"01:39","format":"64Kbps MP3","original":"heretakemyheart_moore_cmp.mp3","mtime":"1414068451","size":"901120","md5":"81eb57638b1bbcadad7e5c2dd462001e","crc32":"b384c05d","sha1":"0f72cb8fab7c5ce9bfa1b692e6dc98a63935bbd9","height":"0","width":"0"},"\/heretakemyheart_moore_dee.mp3":{"source":"original","format":"128Kbps MP3","creator":"Thomas Moore","album":"LibriVox Weekly Poetry","title":"Here, Take my Heart - Read by DEE","length":"93.12","mtime":"1344213030","size":"1491118","md5":"f95ad0e6eb6d2ebf880ca9312c8556a1","crc32":"73398d35","sha1":"7a9f7b4997a10abb637d3158e12895df951c73b6","artist":"Thomas Moore","genre":"Speech","track":"7","external-identifier":"urn:acoustid:unknown","height":"0","width":"0"},"\/heretakemyheart_moore_dee.ogg":{"source":"derivative","format":"Ogg Vorbis","original":"heretakemyheart_moore_dee.mp3","mtime":"1344213294","size":"794609","md5":"4d631664b6265612e0419ba256505997","crc32":"0a042ebe","sha1":"5011cc3f619574cc78d1bf9d1abc8e5f366222db","length":"88.24","height":"0","width":"0"},"\/heretakemyheart_moore_dee.png":{"source":"derivative","format":"PNG","original":"heretakemyheart_moore_dee.ogg","mtime":"1414068526","size":"10485","md5":"9bf3bd22e6271e4ee7ede1d60f639736","crc32":"fe9c677c","sha1":"e21ef813001da66133273f1b816e097b679fcb40"},"\/heretakemyheart_moore_dee_64kb.mp3":{"source":"derivative","creator":"Thomas Moore","title":"Here, Take my Heart - Read by DEE","track":"7","album":"LibriVox Weekly Poetry","genre":"Speech","bitrate":"64","length":"01:33","format":"64Kbps MP3","original":"heretakemyheart_moore_dee.mp3","mtime":"1414068455","size":"855040","md5":"785d9d2ddd5a52803721f0a0449c24ad","crc32":"6dd5e34d","sha1":"ce70dc92d4aeb7bd993feb687ced3f5d6d43d0d1","height":"0","width":"0"},"\/heretakemyheart_moore_dl.mp3":{"source":"original","format":"128Kbps MP3","creator":"Thomas Moore","album":"LibriVox Weekly Poetry","title":"Here, Take My Heart - Read by DL","length":"78.15","mtime":"1344213031","size":"1251630","md5":"ebe1544ef8f89fcd11b2a40f23367a6e","crc32":"7bc5e7f7","sha1":"d125e7c4d2b8114d49c721d7f41af4c15d777aa7","artist":"Thomas Moore","genre":"Speech","track":"8","external-identifier":"urn:acoustid:unknown","height":"0","width":"0"},"\/heretakemyheart_moore_dl.ogg":{"source":"derivative","format":"Ogg Vorbis","original":"heretakemyheart_moore_dl.mp3","mtime":"1344213286","size":"723490","md5":"1ce28723b3c33082c393e8b1f80810a4","crc32":"7e11cb4e","sha1":"c90375e86f638935307f472571815460775a6798","length":"73.73","height":"0","width":"0"},"\/heretakemyheart_moore_dl.png":{"source":"derivative","format":"PNG","original":"heretakemyheart_moore_dl.ogg","mtime":"1414068551","size":"10066","md5":"ea3adf9141e2a28f2b8dade84c94fbc9","crc32":"68a9d2d3","sha1":"7fd418bc871ceca8f0084c1f4e06d61c55bbe52e"},"\/heretakemyheart_moore_dl_64kb.mp3":{"source":"derivative","creator":"Thomas Moore","title":"Here, Take My Heart - Read by DL","track":"8","album":"LibriVox Weekly Poetry","genre":"Speech","bitrate":"64","length":"01:18","format":"64Kbps MP3","original":"heretakemyheart_moore_dl.mp3","mtime":"1414068443","size":"735232","md5":"e48e6f394b9b83e7451730d65acacd11","crc32":"8cede079","sha1":"47086c63932e0348c9c87a6ccc29de283d4a9ed1","height":"0","width":"0"},"\/heretakemyheart_moore_eep.mp3":{"source":"original","format":"128Kbps MP3","creator":"Thomas Moore","album":"LibriVox Weekly Poetry","title":"Here, Take My Heart - Read by EEP","length":"93.75","mtime":"1344213038","size":"1501358","md5":"67acc678bb8daf0e8ace44b424f1005c","crc32":"fe9d4bf9","sha1":"22cd4621165ba6e2886b198e23ae87a1a8c3685f","artist":"Thomas Moore","genre":"Speech","track":"9","external-identifier":"urn:acoustid:unknown","height":"0","width":"0"},"\/heretakemyheart_moore_eep.ogg":{"source":"derivative","format":"Ogg Vorbis","original":"heretakemyheart_moore_eep.mp3","mtime":"1344213397","size":"840728","md5":"9f3e8f4c34c7d7540ff3b993c836672a","crc32":"7af92b69","sha1":"1a58682ba92f5b75383723fa14b5898a6ed5619c","length":"88.37","height":"0","width":"0"},"\/heretakemyheart_moore_eep.png":{"source":"derivative","format":"PNG","original":"heretakemyheart_moore_eep.ogg","mtime":"1414068537","size":"10473","md5":"d8dd7c7343cbacf386633faed481bd3d","crc32":"8bce4298","sha1":"365813ab40db18ca6bcc0ec3fc47f9a2c912d4f7"},"\/heretakemyheart_moore_eep_64kb.mp3":{"source":"derivative","creator":"Thomas Moore","title":"Here, Take My Heart - Read by EEP","track":"9","album":"LibriVox Weekly Poetry","genre":"Speech","bitrate":"64","length":"01:33","format":"64Kbps MP3","original":"heretakemyheart_moore_eep.mp3","mtime":"1414068483","size":"860160","md5":"625d1f2c4aa08cd8a2bf674a2465a8dc","crc32":"0329653b","sha1":"62bb677e6688d3886cabc4b2ca5f59e4ecf8f7e9","height":"0","width":"0"},"\/heretakemyheart_moore_es.mp3":{"source":"original","format":"128Kbps MP3","creator":"Thomas Moore","album":"LibriVox Weekly Poetry","title":"Here, Take My Heart - Read by ES","length":"76.17","mtime":"1344213013","size":"1220910","md5":"10d427aacab7d72771c220802fa503e9","crc32":"53f64eb9","sha1":"270eb24117f8eec307f4fc09a5dbfcaa4e85c8d1","track":"10","artist":"Thomas Moore","genre":"Speech","external-identifier":"urn:acoustid:unknown","height":"0","width":"0"},"\/heretakemyheart_moore_es.ogg":{"source":"derivative","format":"Ogg Vorbis","original":"heretakemyheart_moore_es.mp3","mtime":"1344213390","size":"699779","md5":"0e195f764b8a21e504d0e37293c8bce7","crc32":"a7eac791","sha1":"fc1c48ec31c8b71ece8750d4c984ac519220a6bd","length":"71.17","height":"0","width":"0"},"\/heretakemyheart_moore_es.png":{"source":"derivative","format":"PNG","original":"heretakemyheart_moore_es.ogg","mtime":"1414068530","size":"9410","md5":"9ed458e0222847695f98b8ccb8a4371e","crc32":"4b436535","sha1":"4c4c1d19c22b71252198fa876092b3a17b4c47a6"},"\/heretakemyheart_moore_es_64kb.mp3":{"source":"derivative","creator":"Thomas Moore","title":"Here, Take My Heart - Read by ES","track":"10","album":"LibriVox Weekly Poetry","genre":"Speech","bitrate":"64","length":"01:16","format":"64Kbps MP3","original":"heretakemyheart_moore_es.mp3","mtime":"1414068487","size":"719360","md5":"a19c42e723acce4377a2dc9d1344f9e0","crc32":"bfae9aa2","sha1":"cc3ee0d0e0830fcbd8e7d218ffa7544e21b61132","height":"0","width":"0"},"\/heretakemyheart_moore_fs.mp3":{"source":"original","format":"128Kbps MP3","creator":"Thomas Moore","album":"LibriVox Weekly Poetry","title":"Here, Take My Heart - Read by FS","length":"82.05","mtime":"1344213022","size":"1315118","md5":"47ad32ed853bbf51b1ffb66137d54a6e","crc32":"963dd9cc","sha1":"9454aa81dd3a2f8f6138ac186fb54a3bf0a03f5f","artist":"Thomas Moore","genre":"Speech","track":"11","external-identifier":"urn:acoustid:unknown","height":"0","width":"0"},"\/heretakemyheart_moore_fs.ogg":{"source":"derivative","format":"Ogg Vorbis","original":"heretakemyheart_moore_fs.mp3","mtime":"1344213302","size":"672609","md5":"e544b786a9b60e303c2af102e09c0301","crc32":"99b64674","sha1":"5d6c5bd69b96057d0b615e9544ce7de6558aaeb3","length":"77.57","height":"0","width":"0"},"\/heretakemyheart_moore_fs.png":{"source":"derivative","format":"PNG","original":"heretakemyheart_moore_fs.ogg","mtime":"1414068545","size":"10586","md5":"ce2757f3ee3e4df83d1c275266af50e3","crc32":"daa3055f","sha1":"a7f489819591a2614f595c8559e153cea2edc47a"},"\/heretakemyheart_moore_fs_64kb.mp3":{"source":"derivative","creator":"Thomas Moore","title":"Here, Take My Heart - Read by FS","track":"11","album":"LibriVox Weekly Poetry","genre":"Speech","bitrate":"64","length":"01:22","format":"64Kbps MP3","original":"heretakemyheart_moore_fs.mp3","mtime":"1414068490","size":"766464","md5":"419f6cf46fabefbcd50ef7a8000c56be","crc32":"edfa5f17","sha1":"e3556ddfd22a035744c4d2d3d77aae4d9bb5278c","height":"0","width":"0"},"\/heretakemyheart_moore_hj.mp3":{"source":"original","format":"128Kbps MP3","creator":"Thomas Moore","album":"LibriVox Weekly Poetry","title":"Here, Take My Heart - Read by HJ","length":"68.54","mtime":"1344213014","size":"1097856","md5":"142177b321bebcf586a748040270b0ff","crc32":"bc3cd423","sha1":"f3f52c6f25bc6c5748c20ec56a5d60eda7b2adbb","artist":"Thomas Moore","genre":"Speech","track":"12","external-identifier":"urn:acoustid:unknown","height":"0","width":"0"},"\/heretakemyheart_moore_hj.ogg":{"source":"derivative","format":"Ogg Vorbis","original":"heretakemyheart_moore_hj.mp3","mtime":"1344213280","size":"612982","md5":"41d6b82f619f3e1e7527fe29b9ed1eaf","crc32":"6a4c51e5","sha1":"7e1195a785248f2e3859c6238adbb82c3154d5e4","length":"64.47","height":"0","width":"0"},"\/heretakemyheart_moore_hj.png":{"source":"derivative","format":"PNG","original":"heretakemyheart_moore_hj.ogg","mtime":"1414068533","size":"10800","md5":"6a8f960e0fb5202069c5773c761e45ab","crc32":"bf441036","sha1":"3259a22990a240b1d44e86b26890e14f7ee08f89"},"\/heretakemyheart_moore_hj_64kb.mp3":{"source":"derivative","creator":"Thomas Moore","title":"Here, Take My Heart - Read by HJ","track":"12","album":"LibriVox Weekly Poetry","genre":"Speech","bitrate":"64","length":"01:08","format":"64Kbps MP3","original":"heretakemyheart_moore_hj.mp3","mtime":"1414068438","size":"658432","md5":"568effedae193d5fa8f1eaf79a1a470b","crc32":"346eda41","sha1":"a3e661f9f2cc0db171d3faefeff595ce0e8fbeca","height":"0","width":"0"},"\/heretakemyheart_moore_jcm.mp3":{"source":"original","format":"128Kbps MP3","creator":"Thomas Moore","album":"LibriVox Weekly Poetry","title":"Here, Take My Heart - Read by JCM","length":"70.45","mtime":"1344213028","size":"1128622","md5":"626f3fa4936781448e6fd1e4b0fd55c5","crc32":"2d647cf3","sha1":"3a20530fe670a7f59be1b83aa9c98df798305f00","artist":"Thomas Moore","genre":"Speech","track":"13","external-identifier":"urn:acoustid:unknown","height":"0","width":"0"},"\/heretakemyheart_moore_jcm.ogg":{"source":"derivative","format":"Ogg Vorbis","original":"heretakemyheart_moore_jcm.mp3","mtime":"1344213264","size":"610669","md5":"df89afd95b937a1b1a24c03ad6d71b53","crc32":"c93e26e6","sha1":"2dca2beeeed7169ce038304356dba5fd4e14d614","length":"66.15","height":"0","width":"0"},"\/heretakemyheart_moore_jcm.png":{"source":"derivative","format":"PNG","original":"heretakemyheart_moore_jcm.ogg","mtime":"1414068542","size":"8546","md5":"d14b558e750d72035a7524673fb27bac","crc32":"69ba9979","sha1":"179a6f54240a758ecdc2c804c99ff2a7cb511a0d"},"\/heretakemyheart_moore_jcm_64kb.mp3":{"source":"derivative","creator":"Thomas Moore","title":"Here, Take My Heart - Read by JCM","track":"13","album":"LibriVox Weekly Poetry","genre":"Speech","bitrate":"64","length":"01:10","format":"64Kbps MP3","original":"heretakemyheart_moore_jcm.mp3","mtime":"1414068494","size":"673792","md5":"63d42f5628d84534f8acf273022e0b15","crc32":"8378dbf4","sha1":"03f220fd0e64b1760b83e8bbbcf996c221f5efa9","height":"0","width":"0"},"\/heretakemyheart_moore_jm2.mp3":{"source":"original","format":"128Kbps MP3","creator":"Thomas Moore","album":"LibriVox Weekly Poetry","title":"Here, Take My Heart - Read by JM2","length":"78.08","mtime":"1344213012","size":"1251630","md5":"dace6c685dfdf1eb10e21db4cfb6a3ba","crc32":"b074a3ca","sha1":"e21542735664759fa688b54374a998fcb8b2b533","artist":"Thomas Moore","genre":"Speech","track":"14","external-identifier":"urn:acoustid:unknown","height":"0","width":"0"},"\/heretakemyheart_moore_jm2.ogg":{"source":"derivative","format":"Ogg Vorbis","original":"heretakemyheart_moore_jm2.mp3","mtime":"1344213249","size":"728268","md5":"70478b4431d904538aa9b09176fc7176","crc32":"8e0f6437","sha1":"127c0a0f1b2dfe5dafe1119bf123a4c7d73891e7","length":"74.06","height":"0","width":"0"},"\/heretakemyheart_moore_jm2.png":{"source":"derivative","format":"PNG","original":"heretakemyheart_moore_jm2.ogg","mtime":"1414068548","size":"10555","md5":"dd259cf39e7a8baaef44088de89032d5","crc32":"4d352dff","sha1":"09ccc76bbb346b9ef1a747c95af81b1a07ce7b2c"},"\/heretakemyheart_moore_jm2_64kb.mp3":{"source":"derivative","creator":"Thomas Moore","title":"Here, Take My Heart - Read by JM2","track":"14","album":"LibriVox Weekly Poetry","genre":"Speech","bitrate":"64","length":"01:18","format":"64Kbps MP3","original":"heretakemyheart_moore_jm2.mp3","mtime":"1414068459","size":"734720","md5":"cb82944be616938ed8ec2e1cdd87b854","crc32":"0967c286","sha1":"2127f282f88cf2e0c55fa83b0cbb60a427a84678","height":"0","width":"0"},"\/heretakemyheart_moore_jn.mp3":{"source":"original","format":"128Kbps MP3","creator":"Thomas Moore","album":"LibriVox Weekly Poetry","title":"Here, Take My Heart - Read by JN","length":"74.24","mtime":"1344213027","size":"1190016","md5":"de509981778f99e008457b358698ac3a","crc32":"e255d777","sha1":"4b6a7263139287a28eb4b83b9b142499cc25fa0e","artist":"Thomas Moore","genre":"Speech","track":"15","external-identifier":"urn:acoustid:unknown","height":"0","width":"0"},"\/heretakemyheart_moore_jn.ogg":{"source":"derivative","format":"Ogg Vorbis","original":"heretakemyheart_moore_jn.mp3","mtime":"1344213309","size":"666031","md5":"ec14d3e3afd74e816954b86329509cd3","crc32":"6718543f","sha1":"2b172c3eaf4ecb739f9c172a327d4380c61ffd65","length":"69.98","height":"0","width":"0"},"\/heretakemyheart_moore_jn.png":{"source":"derivative","format":"PNG","original":"heretakemyheart_moore_jn.ogg","mtime":"1414068553","size":"10447","md5":"1b6ce47c64760375588a6a5a8c24e797","crc32":"23133c36","sha1":"41c9d0dcef7e88c28a7e144d8780a3c9f82f05f3"},"\/heretakemyheart_moore_jn_64kb.mp3":{"source":"derivative","creator":"Thomas Moore","title":"Here, Take My Heart - Read by JN","track":"15","album":"LibriVox Weekly Poetry","genre":"Speech","bitrate":"64","length":"01:14","format":"64Kbps MP3","original":"heretakemyheart_moore_jn.mp3","mtime":"1414068504","size":"704000","md5":"b6ee8c6b42f6f510cd7d224b1a47efe7","crc32":"ff001bb8","sha1":"507e6a358a0357e78700d5fd2bf7bb4011cc07bb","height":"0","width":"0"},"\/heretakemyheart_moore_jo.mp3":{"source":"original","format":"128Kbps MP3","creator":"Thomas Moore","album":"LibriVox Weekly Poetry","title":"Here, Take My Heart - Read by JO","length":"77.06","mtime":"1344213007","size":"1235246","md5":"3696ea82eb25b855e8d9a7967f536257","crc32":"91388167","sha1":"2689e5f8527bcbb41d4a741ab91f43bd275217f3","track":"16","genre":"Speech","artist":"Thomas Moore","external-identifier":"urn:acoustid:unknown","height":"0","width":"0"},"\/heretakemyheart_moore_jo.ogg":{"source":"derivative","format":"Ogg Vorbis","original":"heretakemyheart_moore_jo.mp3","mtime":"1344213420","size":"711833","md5":"17c5343df4aaa1f7c6301aa06d232f42","crc32":"e5ebd3d0","sha1":"f462bf6730b3aadcaa382cc54b4f3d03133f8f92","length":"72.66","height":"0","width":"0"},"\/heretakemyheart_moore_jo.png":{"source":"derivative","format":"PNG","original":"heretakemyheart_moore_jo.ogg","mtime":"1414068523","size":"11325","md5":"eb5b9e01e2592eede30ad58b9181377a","crc32":"31a53e71","sha1":"d08335a2477956d48c4348f5c57fb231f6e70c50"},"\/heretakemyheart_moore_jo_64kb.mp3":{"source":"derivative","creator":"Thomas Moore","title":"Here, Take My Heart - Read by JO","track":"16","album":"LibriVox Weekly Poetry","genre":"Speech","bitrate":"64","length":"01:17","format":"64Kbps MP3","original":"heretakemyheart_moore_jo.mp3","mtime":"1414068501","size":"726528","md5":"1ef0447f74aa52cc355902c8e690e05e","crc32":"8f916d87","sha1":"5a6e7d587550599c4843c038c645145dac8b353c","height":"0","width":"0"},"\/heretakemyheart_moore_joc.mp3":{"source":"original","format":"128Kbps MP3","creator":"Thomas Moore","album":"LibriVox Weekly Poetry","title":"Here, Take My Heart - Read by JOC","length":"85.89","mtime":"1344213008","size":"1376256","md5":"d6896a2128107869b5b2889db2b6e5c8","crc32":"13b88d14","sha1":"121d5385fe35069c5bfaff1418bdd51441ccb999","artist":"Thomas Moore","genre":"Speech","track":"17","external-identifier":"urn:acoustid:unknown","height":"0","width":"0"},"\/heretakemyheart_moore_joc.ogg":{"source":"derivative","format":"Ogg Vorbis","original":"heretakemyheart_moore_joc.mp3","mtime":"1344213316","size":"745090","md5":"12a4fe2d2124ff54f56e3a2f3f009a9a","crc32":"56298c03","sha1":"fc386d1be44ee45358e48e88a748f45e095ce72c","length":"80.44","height":"0","width":"0"},"\/heretakemyheart_moore_joc.png":{"source":"derivative","format":"PNG","original":"heretakemyheart_moore_joc.ogg","mtime":"1414068570","size":"10947","md5":"c51859e65a8e2ca5b634b546f3e34cd4","crc32":"b54eaf79","sha1":"437172c0665a6559f67ba885ac813c01510d7320"},"\/heretakemyheart_moore_joc_64kb.mp3":{"source":"derivative","creator":"Thomas Moore","title":"Here, Take My Heart - Read by JOC","track":"17","album":"LibriVox Weekly Poetry","genre":"Speech","bitrate":"64","length":"01:26","format":"64Kbps MP3","original":"heretakemyheart_moore_joc.mp3","mtime":"1414068519","size":"797184","md5":"b2c086b934f1fd1ab5d9efcbb2b5467b","crc32":"88943da2","sha1":"c569e3daadf0f0731434171684cbe8085959fefe","height":"0","width":"0"},"\/heretakemyheart_moore_lah.mp3":{"source":"original","format":"128Kbps MP3","creator":"Thomas Moore","album":"LibriVox Weekly Poetry","title":"Here, Take My Heart - Read by LAH","length":"83.01","mtime":"1344213010","size":"1329326","md5":"669813f67b7c057622c25165f383b9f6","crc32":"d2eb674e","sha1":"c84356643cfb4ca59ae6aac45042da5b6e954eab","genre":"Speech","artist":"Thomas Moore","track":"18","external-identifier":"urn:acoustid:unknown","height":"0","width":"0"},"\/heretakemyheart_moore_lah.ogg":{"source":"derivative","format":"Ogg Vorbis","original":"heretakemyheart_moore_lah.mp3","mtime":"1344213342","size":"746137","md5":"67201b7a33b97cea3581c53df8d10175","crc32":"6899000c","sha1":"31e76a2fd66706f9ead5e1ee226c5925c98ed35b","length":"77.74","height":"0","width":"0"},"\/heretakemyheart_moore_lah.png":{"source":"derivative","format":"PNG","original":"heretakemyheart_moore_lah.ogg","mtime":"1414068557","size":"10700","md5":"f425f404dc7dd66e8f90cb381234675b","crc32":"44d23240","sha1":"cbdea81615d349ced2bfd86ce5262bd1cce04b05"},"\/heretakemyheart_moore_lah_64kb.mp3":{"source":"derivative","creator":"Thomas Moore","title":"Here, Take My Heart - Read by LAH","track":"18","album":"LibriVox Weekly Poetry","genre":"Speech","bitrate":"64","length":"01:23","format":"64Kbps MP3","original":"heretakemyheart_moore_lah.mp3","mtime":"1414068475","size":"774144","md5":"64ab076ec30a531fa1d3e0e8c528ccc9","crc32":"c860942d","sha1":"c72b6bb8ec61d145832a9c4627cfbf1967593abc","height":"0","width":"0"},"\/heretakemyheart_moore_llw.mp3":{"source":"original","format":"128Kbps MP3","creator":"Thomas Moore","album":"LibriVox Weekly Poetry","title":"Here, Take My Heart - Read by LLW","length":"92.1","mtime":"1344213021","size":"1474688","md5":"0b4cf3c8d4daaacf7c4ca916cc86fab2","crc32":"e63dc578","sha1":"7041c704e17f1f061edfacd2a2770411fddfa960","artist":"Thomas Moore","genre":"Speech","track":"19","external-identifier":"urn:acoustid:unknown","height":"0","width":"0"},"\/heretakemyheart_moore_llw.ogg":{"source":"derivative","format":"Ogg Vorbis","original":"heretakemyheart_moore_llw.mp3","mtime":"1344213358","size":"833070","md5":"245be202120f57ca23b4ceec9fa81049","crc32":"4b37498f","sha1":"330c8a00ba3233b5c528b20215af21284e9e88e7","length":"87.1","height":"0","width":"0"},"\/heretakemyheart_moore_llw.png":{"source":"derivative","format":"PNG","original":"heretakemyheart_moore_llw.ogg","mtime":"1414068564","size":"10570","md5":"999be62fb704b75d5dcb09ea7dabae8f","crc32":"e094921a","sha1":"effda911038f5159321ff894b8edc4e9207fba35"},"\/heretakemyheart_moore_llw_64kb.mp3":{"source":"derivative","creator":"Thomas Moore","title":"Here, Take My Heart - Read by LLW","track":"19","album":"LibriVox Weekly Poetry","genre":"Speech","bitrate":"64","length":"01:32","format":"64Kbps MP3","original":"heretakemyheart_moore_llw.mp3","mtime":"1414068447","size":"846848","md5":"ce98948e7f1d3714ead92d630cc3f9b1","crc32":"0a0cba64","sha1":"eb83aa599ead98a905f9c7f8013264ad22dcff0e","height":"0","width":"0"},"\/heretakemyheart_moore_mlb.mp3":{"source":"original","format":"128Kbps MP3","creator":"Thomas Moore","album":"LibriVox Weekly Poetry","title":"Here, Take My Heart - Read by MLB","length":"95.24","mtime":"1344213017","size":"1525760","md5":"dc54accc2a3cb249c3a26d3b9df53d2f","crc32":"703fc8d2","sha1":"d50181e7750a75b96d54b87f37c2eed885a87273","artist":"Thomas Moore","genre":"Speech","track":"20","external-identifier":"urn:acoustid:unknown","height":"0","width":"0"},"\/heretakemyheart_moore_mlb.ogg":{"source":"derivative","format":"Ogg Vorbis","original":"heretakemyheart_moore_mlb.mp3","mtime":"1344213367","size":"879573","md5":"79d5da801316cb65c5d8cff5a43ac68b","crc32":"7bb3a467","sha1":"3f1d3917f0d6987a14ed451280dca78b2ffeb5a5","length":"90.92","height":"0","width":"0"},"\/heretakemyheart_moore_mlb.png":{"source":"derivative","format":"PNG","original":"heretakemyheart_moore_mlb.ogg","mtime":"1414068561","size":"12129","md5":"3ec4f09b0b52cae5db001a9c0cba4162","crc32":"5cb2928d","sha1":"a7e50754872a81a7a2e559dec2e248886a79c467"},"\/heretakemyheart_moore_mlb_64kb.mp3":{"source":"derivative","creator":"Thomas Moore","title":"Here, Take My Heart - Read by MLB","track":"20","album":"LibriVox Weekly Poetry","genre":"Speech","bitrate":"64","length":"01:35","format":"64Kbps MP3","original":"heretakemyheart_moore_mlb.mp3","mtime":"1414068498","size":"871936","md5":"13505163b6e507dd41f35e04b6373dea","crc32":"229fd477","sha1":"4fa56e2f12006a4b7b7fb7221147cc8cbce02f88","height":"0","width":"0"},"\/heretakemyheart_moore_rds.mp3":{"source":"original","format":"128Kbps MP3","creator":"Thomas Moore","album":"LibriVox Weekly Poetry","title":"Here, Take My Heart - Read by RDS","length":"104.3","mtime":"1344213025","size":"1671470","md5":"0ccbb3da63c68b6e8d75a0079ce8e992","crc32":"55ae744e","sha1":"86cdffdf1e736902ec537a756b65513d48c93bef","artist":"Thomas Moore","genre":"Speech","track":"21","external-identifier":"urn:acoustid:unknown","height":"0","width":"0"},"\/heretakemyheart_moore_rds.ogg":{"source":"derivative","format":"Ogg Vorbis","original":"heretakemyheart_moore_rds.mp3","mtime":"1344213335","size":"939151","md5":"f67e9e108f66a5282de83bc174819618","crc32":"c39b0819","sha1":"405cfd989745fd226bc4fcbfbf22dbdb00036096","length":"99.86","height":"0","width":"0"},"\/heretakemyheart_moore_rds.png":{"source":"derivative","format":"PNG","original":"heretakemyheart_moore_rds.ogg","mtime":"1414068588","size":"10975","md5":"855deb88e87e9f84652f3eac13e844df","crc32":"2a0b161e","sha1":"4b5a586fc1b5a7a412a3da14ff542dba4ff33357"},"\/heretakemyheart_moore_rds_64kb.mp3":{"source":"derivative","creator":"Thomas Moore","title":"Here, Take My Heart - Read by RDS","track":"21","album":"LibriVox Weekly Poetry","genre":"Speech","bitrate":"64","length":"01:44","format":"64Kbps MP3","original":"heretakemyheart_moore_rds.mp3","mtime":"1414068516","size":"944640","md5":"13949b9c12ef96e299a38200d93feac2","crc32":"ea7d9325","sha1":"a8249a00f086944311dd169ec7ffd62094a119f1","height":"0","width":"0"},"\/heretakemyheart_moore_ref.mp3":{"source":"original","format":"128Kbps MP3","creator":"Thomas Moore","album":"LibriVox Weekly Poetry","title":"Here, Take My Heart - Read by REF","length":"91.19","mtime":"1344213005","size":"1460526","md5":"5407de1a1afe10df4b1ad86c1e0ef458","crc32":"98efa184","sha1":"2fd7bdc4d5e5f95199db0db52dcc517e9f5b73d9","artist":"Thomas Moore","genre":"Speech","track":"22","external-identifier":"urn:acoustid:unknown","height":"0","width":"0"},"\/heretakemyheart_moore_ref.ogg":{"source":"derivative","format":"Ogg Vorbis","original":"heretakemyheart_moore_ref.mp3","mtime":"1344213405","size":"852588","md5":"c6d339c5edeb26dff37e385b02b08ca7","crc32":"b6ffc27d","sha1":"7e640dab601229fc3c516f0fa7b9fbdfea7b21c0","length":"86.28","height":"0","width":"0"},"\/heretakemyheart_moore_ref.png":{"source":"derivative","format":"PNG","original":"heretakemyheart_moore_ref.ogg","mtime":"1414068578","size":"9857","md5":"2a06e771080e83793ec03d7363f95a88","crc32":"45cd4b68","sha1":"7dc83125e6b077f6315ab1be6a0a86fa74525354"},"\/heretakemyheart_moore_ref_64kb.mp3":{"source":"derivative","creator":"Thomas Moore","title":"Here, Take My Heart - Read by REF","track":"22","album":"LibriVox Weekly Poetry","genre":"Speech","bitrate":"64","length":"01:31","format":"64Kbps MP3","original":"heretakemyheart_moore_ref.mp3","mtime":"1414068512","size":"839680","md5":"9031a5dbe885447b682e7bb80f77dea3","crc32":"0b917647","sha1":"55e950faef0430e76c8bf174e2c7c82d04849999","height":"0","width":"0"},"\/heretakemyheart_moore_rn.mp3":{"source":"original","format":"128Kbps MP3","creator":"Thomas Moore","album":"LibriVox Weekly Poetry","title":"Here, Take My Heart - Read by RN","length":"97.43","mtime":"1344213035","size":"1560704","md5":"9320078014d3f86d9339a41f1f9b972b","crc32":"b3205639","sha1":"b042dd09c059a9dd28c674acaa05e82e823c0ee7","track":"23","artist":"Thomas Moore","genre":"Speech","external-identifier":"urn:acoustid:unknown","height":"0","width":"0"},"\/heretakemyheart_moore_rn.ogg":{"source":"derivative","format":"Ogg Vorbis","original":"heretakemyheart_moore_rn.mp3","mtime":"1344213383","size":"893646","md5":"6567476973b956e9bf9d4ed413ed8afe","crc32":"e7e02106","sha1":"f706c5378151c03ccf923c8b2190c78c89de6ab5","length":"92.5","height":"0","width":"0"},"\/heretakemyheart_moore_rn.png":{"source":"derivative","format":"PNG","original":"heretakemyheart_moore_rn.ogg","mtime":"1414068574","size":"9493","md5":"18f78c5831f487f8c52e057ee6c77951","crc32":"d926c37f","sha1":"0251d530d2c8cf1455cd00ebd8979efc32ce378b"},"\/heretakemyheart_moore_rn_64kb.mp3":{"source":"derivative","creator":"Thomas Moore","title":"Here, Take My Heart - Read by RN","track":"23","album":"LibriVox Weekly Poetry","genre":"Speech","bitrate":"64","length":"01:37","format":"64Kbps MP3","original":"heretakemyheart_moore_rn.mp3","mtime":"1414068508","size":"889344","md5":"1a2bc9dc5b497d06a44cf149b7dab147","crc32":"623b11f4","sha1":"4fcf8c92da1b916bd9f2c99cf89366704dcab788","height":"0","width":"0"}},
"misc":
{"css":"audio","image":"https:\/\/ia600605.us.archive.org\/35\/items\/here_takemyheart_1208_librivox\/Here_Take_Heart_1209_thumb.jpg","header_image":"https:\/\/ia600501.us.archive.org\/1\/items\/librivoxaudio\/libvox.png","collection-title":"The LibriVox Free Audiobook Collection"},
"creativecommons":
{"name":"Public Domain Mark 1.0","license_url":"http:\/\/creativecommons.org\/publicdomain\/mark\/1.0\/","image_url":"http:\/\/i.creativecommons.org\/p\/mark\/1.0\/88x31.png","embed_text":"<?xml version=\"1.0\" encoding=\"utf-8\"?>\n<rdf:RDF\n  xmlns:foaf='http:\/\/xmlns.com\/foaf\/0.1\/'\n  xmlns:cc='http:\/\/creativecommons.org\/ns#'\n  xmlns:rdf='http:\/\/www.w3.org\/1999\/02\/22-rdf-syntax-ns#'\n  xmlns:dc='http:\/\/purl.org\/dc\/elements\/1.1\/'\n  xmlns:dcq='http:\/\/purl.org\/dc\/terms\/'\n>\n  <cc:License rdf:about=\"http:\/\/creativecommons.org\/publicdomain\/mark\/1.0\/\">\n    <cc:permits rdf:resource=\"http:\/\/creativecommons.org\/ns#Reproduction\"\/>\n    <cc:permits rdf:resource=\"http:\/\/creativecommons.org\/ns#DerivativeWorks\"\/>\n    <cc:permits rdf:resource=\"http:\/\/creativecommons.org\/ns#Distribution\"\/>\n    <dc:identifier>mark<\/dc:identifier>\n    <dcq:hasVersion>1.0<\/dcq:hasVersion>\n    <foaf:logo rdf:resource=\"http:\/\/i.creativecommons.org\/p\/mark\/1.0\/80x15.png\"\/>\n    <foaf:logo rdf:resource=\"http:\/\/i.creativecommons.org\/p\/mark\/1.0\/88x31.png\"\/>\n    <cc:licenseClass rdf:resource=\"http:\/\/creativecommons.org\/license\/publicdomain\/\"\/>\n    <dc:title xml:lang=\"be\">Public Domain Mark 1.0<\/dc:title>\n    <dc:title xml:lang=\"bn\">Public Domain Mark 1.0<\/dc:title>\n    <dc:title xml:lang=\"ast-es\">Public Domain Mark 1.0<\/dc:title>\n    <dc:title xml:lang=\"en-ca\">Public Domain Mark 1.0<\/dc:title>\n    <dc:title xml:lang=\"bg\">Public Domain Mark 1.0<\/dc:title>\n    <dc:title xml:lang=\"cs\">Public Domain Mark 1.0<\/dc:title>\n    <dc:title xml:lang=\"ar\">Public Domain Mark 1.0<\/dc:title>\n    <dc:title xml:lang=\"eo\">Public Domain Mark 1.0<\/dc:title>\n    <dc:title xml:lang=\"fi\">Public Domain Mark 1.0<\/dc:title>\n    <dc:title xml:lang=\"it\">Public Domain Mark 1.0<\/dc:title>\n    <dc:title xml:lang=\"sv\">Public Domain Mark 1.0<\/dc:title>\n    <dc:title xml:lang=\"sl\">Public Domain Mark 1.0<\/dc:title>\n    <dc:title xml:lang=\"de-ch\">Public Domain Mark 1.0<\/dc:title>\n    <dc:title xml:lang=\"da\">Public Domain Mark 1.0<\/dc:title>\n    <dc:title xml:lang=\"en-hk\">Public Domain Mark 1.0<\/dc:title>\n    <dc:title xml:lang=\"i18n\">${licenses.publicdomain_mark_title} 1.0<\/dc:title>\n    <dc:title xml:lang=\"en\">Public Domain Mark 1.0<\/dc:title>\n    <dc:title xml:lang=\"mk\">Public Domain Mark 1.0<\/dc:title>\n    <dc:title xml:lang=\"it-ch\">Public Domain Mark 1.0<\/dc:title>\n    <dc:title xml:lang=\"fr-ch\">Public Domain Mark 1.0<\/dc:title>\n    <dc:title xml:lang=\"nl\">Public Domain Mark 1.0<\/dc:title>\n    <dc:title xml:lang=\"eu\">Public Domain Mark 1.0<\/dc:title>\n    <dc:title xml:lang=\"hy\">Public Domain Mark 1.0<\/dc:title>\n    <dc:title xml:lang=\"el\">Public Domain Mark 1.0<\/dc:title>\n    <dc:title xml:lang=\"vi\">Public Domain Mark 1.0<\/dc:title>\n    <dc:title xml:lang=\"es-pr\">Public Domain Mark 1.0<\/dc:title>\n    <dc:title xml:lang=\"id\">Public Domain Mark 1.0<\/dc:title>\n    <dc:title xml:lang=\"he\">Public Domain Mark 1.0<\/dc:title>\n    <dc:title xml:lang=\"lv\">Public Domain Mark 1.0<\/dc:title>\n    <dc:title xml:lang=\"lt\">Public Domain Mark 1.0<\/dc:title>\n    <dc:title xml:lang=\"oci-es\">Public Domain Mark 1.0<\/dc:title>\n    <dc:title xml:lang=\"th\">Public Domain Mark 1.0<\/dc:title>\n    <dc:title xml:lang=\"sr-latn\">Public Domain Mark 1.0<\/dc:title>\n    <dc:title xml:lang=\"ta\">Public Domain Mark 1.0<\/dc:title>\n    <dc:title xml:lang=\"es-ec\">Public Domain Mark 1.0<\/dc:title>\n    <dc:title xml:lang=\"zh-tw\">Public Domain Mark 1.0<\/dc:title>\n    <dc:title xml:lang=\"az\">Public Domain Mark 1.0<\/dc:title>\n    <dc:title xml:lang=\"es-pe\">Public Domain Mark 1.0<\/dc:title>\n    <dc:title xml:lang=\"pt-br\">Public Domain Mark 1.0<\/dc:title>\n    <dc:title xml:lang=\"es-co\">Public Domain Mark 1.0<\/dc:title>\n    <dc:title xml:lang=\"no\">Public Domain Mark 1.0<\/dc:title>\n    <dc:title xml:lang=\"es-gt\">Public Domain Mark 1.0<\/dc:title>\n    <dc:title xml:lang=\"es-cl\">Public Domain Mark 1.0<\/dc:title>\n    <dc:title xml:lang=\"ur\">Public Domain Mark 1.0<\/dc:title>\n    <dc:title xml:lang=\"de\">Public Domain Mark 1.0<\/dc:title>\n    <dc:title xml:lang=\"hu\">Public Domain Mark 1.0<\/dc:title>\n    <dc:title xml:lang=\"es\">Public Domain Mark 1.0<\/dc:title>\n    <dc:title xml:lang=\"fr-lu\">Public Domain Mark 1.0<\/dc:title>\n    <dc:title xml:lang=\"hr\">Public Domain Mark 1.0<\/dc:title>\n    <dc:title xml:lang=\"as\">Public Domain Mark 1.0<\/dc:title>\n    <dc:title xml:lang=\"en-sg\">Public Domain Mark 1.0<\/dc:title>\n    <dc:title xml:lang=\"zh-hk\">Public Domain Mark 1.0<\/dc:title>\n    <dc:title xml:lang=\"en-gb\">Public Domain Mark 1.0<\/dc:title>\n    <dc:title xml:lang=\"es-ar\">Public Domain Mark 1.0<\/dc:title>\n    <dc:title xml:lang=\"zu\">Public Domain Mark 1.0<\/dc:title>\n    <dc:title xml:lang=\"de-at\">Public Domain Mark 1.0<\/dc:title>\n    <dc:title xml:lang=\"ca\">Public Domain Mark 1.0<\/dc:title>\n    <dc:title xml:lang=\"pt-pt\">Public Domain Mark 1.0<\/dc:title>\n    <dc:title xml:lang=\"ms\">Public Domain Mark 1.0<\/dc:title>\n    <dc:title xml:lang=\"pt\">Public Domain Mark 1.0<\/dc:title>\n    <dc:title xml:lang=\"pl\">Public Domain Mark 1.0<\/dc:title>\n    <dc:title xml:lang=\"ga\">Public Domain Mark 1.0<\/dc:title>\n    <dc:title xml:lang=\"es-mx\">Public Domain Mark 1.0<\/dc:title>\n    <dc:title xml:lang=\"zh\">Public Domain Mark 1.0<\/dc:title>\n    <dc:title xml:lang=\"gl\">Public Domain Mark 1.0<\/dc:title>\n    <dc:title xml:lang=\"fr-ca\">Public Domain Mark 1.0<\/dc:title>\n    <dc:title xml:lang=\"tr\">Public Domain Mark 1.0<\/dc:title>\n    <dc:title xml:lang=\"en-us\">Public Domain Mark 1.0<\/dc:title>\n    <dc:title xml:lang=\"ru\">Public Domain Mark 1.0<\/dc:title>\n    <dc:title xml:lang=\"is\">Public Domain Mark 1.0<\/dc:title>\n    <dc:title xml:lang=\"af\">Public Domain Mark 1.0<\/dc:title>\n    <dc:title xml:lang=\"uk\">Public Domain Mark 1.0<\/dc:title>\n    <dc:title xml:lang=\"hi\">Public Domain Mark 1.0<\/dc:title>\n    <dc:title xml:lang=\"nso\">Public Domain Mark 1.0<\/dc:title>\n    <dc:title xml:lang=\"sr\">Public Domain Mark 1.0<\/dc:title>\n    <dc:title xml:lang=\"ro\">Public Domain Mark 1.0<\/dc:title>\n    <dc:title xml:lang=\"ko\">Public Domain Mark 1.0<\/dc:title>\n    <dc:title xml:lang=\"mn\">Public Domain Mark 1.0<\/dc:title>\n    <dc:title xml:lang=\"fr\">Public Domain Mark 1.0<\/dc:title>\n    <dc:title xml:lang=\"ja\">Public Domain Mark 1.0<\/dc:title>\n  <\/cc:License>\n<\/rdf:RDF>"},
"item":
{"downloads":2254,"week":8,"month":44}}