{
"server":"ia902707.us.archive.org",
"dir":"/35/items/thricetoss_1302_librivox",
"metadata":{"collection":["librivoxaudio","audio_bookspoetry","opensource_audio"],"mediatype":["audio"],"title":["Thrice Toss Those Oaken Ashes in the Air"],"creator":["Thomas Campion"],"taper":["LibriVox"],"source":["Librivox recording of a public-domain text"],"identifier":["thricetoss_1302_librivox"],"addeddate":["2013-02-17 17:55:05"],"publicdate":["2013-02-17 17:55:14"],"description":["<a href=\"http:\/\/librivox.org\/\" rel=\"nofollow\">LibriVox<\/a> volunteers bring you 13 recordings of Thrice Toss Those Oaken Ashes in the Air by Thomas Campion. \nThis was the Weekly Poetry project for February 10, 2013.\n\nThomas Campion was an English composer, poet, and physician. He wrote over a hundred lute songs; masques for dancing, and an authoritative technical treatise on music. (Summary by D. Lawrence)\n\nFor further information, including links to online text, reader information, RSS feeds, CD cover or other formats (if available), please go to the <a href=\"http:\/\/librivox.org\/thrice-toss-those-oaken-ashes-in-the-air-by-thomas-campion\/\" rel=\"nofollow\">LibriVox catalog page<\/a> for this recording. \n\nFor more free audio books or to become a volunteer reader, visit <a href=\"http:\/\/librivox.org\/\" rel=\"nofollow\">LibriVox.org<\/a>.\n\n<a href=\"http:\/\/archive.org\/download\/LibrivoxM4bCollectionAudiobooks_13\/ThriceTossThoseOakenAshesInTheAir.m4b\" rel=\"nofollow\">Download M4B (7MB)<\/a><br \/>"],"date":["25013-02-17"],"year":["2501"],"subject":["librivox; literature; audiobook; poetry; fantasy; myths\/legends; nature; romance"],"licenseurl":["http:\/\/creativecommons.org\/publicdomain\/mark\/1.0\/"],"curation":["[curator]malware@archive.org[\/curator][date]20140323075206[\/date][comment]checked for malware[\/comment]"],"boxid":["OL100020508"]},
"files":
{"\/Thrice_Toss_1306.jpg":{"source":"original","format":"JPEG","mtime":"1372537640","size":"66821","md5":"cd3c8b94e6da558cbcc6aa187a6d0a89","crc32":"1319a21e","sha1":"df96a17a0d0381f349cd5b822466c9bc909d7d90"},"\/Thrice_Toss_1306_thumb.jpg":{"source":"derivative","format":"JPEG Thumb","original":"Thrice_Toss_1306.jpg","mtime":"1414333831","size":"8527","md5":"4008ee29a4ad8c3d7523c725380be06b","crc32":"deb6e33c","sha1":"33ddc6ac41521df570d3837d0a1306790df05421"},"\/oaken_ashes_1302_librivox_files.xml":{"source":"original","format":"Metadata","mtime":"1361123702","size":"3133","md5":"28a3cb8817c8c3ad555a176b9825d697","crc32":"d6581ee4","sha1":"d7047b1eaf278ce761245a565aba9db57813d385"},"\/oaken_ashes_1302_librivox_meta.xml":{"source":"original","format":"Metadata","mtime":"1361123702","size":"428","md5":"eb1039293d71e768122d52a03b70cfd4","crc32":"10524db9","sha1":"4bd6feff3d95cfa18a14a518269fc8450e7beffa"},"\/oakenashes_1302_librivox_files.xml":{"source":"original","format":"Metadata","mtime":"1361123701","size":"3133","md5":"28a3cb8817c8c3ad555a176b9825d697","crc32":"d6581ee4","sha1":"d7047b1eaf278ce761245a565aba9db57813d385"},"\/oakenashes_1302_librivox_meta.xml":{"source":"original","format":"Metadata","mtime":"1361123701","size":"428","md5":"eb1039293d71e768122d52a03b70cfd4","crc32":"10524db9","sha1":"4bd6feff3d95cfa18a14a518269fc8450e7beffa"},"\/thricetoss_1302_librivox_archive.torrent":{"source":"original","btih":"dc094d9be44270b12205d45cbe45ec756e3f2c5b","mtime":"1420872761","size":"20290","md5":"1eb8ca1924855e53f36e427453336d1c","crc32":"fe355fe5","sha1":"9b0d40ab3b37910a5304ef6e5b1a8423a45d3bdf","format":"Archive BitTorrent"},"\/thricetoss_1302_librivox_files.xml":{"source":"original","format":"Metadata","md5":"972f21be8a0bb51fe8b3cc7e9e74ed6a"},"\/thricetoss_1302_librivox_meta.xml":{"source":"original","format":"Metadata","mtime":"1420872753","size":"2051","md5":"687d3d06f8d7e1e75db1377d0b84b72d","crc32":"7dc6e734","sha1":"ac8f55d192149de971de7dad8f26d04c462c7f9b"},"\/thricetoss_campion_da.mp3":{"source":"original","format":"128Kbps MP3","creator":"Thomas Campion","album":"LibriVox Weekly Poetry","title":"Thrice Toss Those Oaken Ashes in the Air - Read by DBL","length":"65.2","mtime":"1361123702","size":"1044782","md5":"210e3aa19e97d856262961d2879130a2","crc32":"34553159","sha1":"c1009a51a8b483b956b9f3d324e06f6d60feb48e","artist":"Thomas Campion","track":"1","genre":"Speech","external-identifier":"urn:acoustid:unknown","height":"0","width":"0"},"\/thricetoss_campion_da.ogg":{"source":"derivative","format":"Ogg Vorbis","original":"thricetoss_campion_da.mp3","mtime":"1361123790","size":"608462","md5":"cc1a872095338eac925ff27c3f2e0f3d","crc32":"f50b3e81","sha1":"eb7d09f2474b7245c0dfbbd5859857b50aa8a8f9","length":"65.18","height":"0","width":"0"},"\/thricetoss_campion_da.png":{"source":"derivative","format":"PNG","original":"thricetoss_campion_da.mp3","mtime":"1420872500","size":"10060","md5":"ce48cbc0c2394097ee6946915a6a89b5","crc32":"dbcac3b4","sha1":"0da3ae2e771663a56a9b91512701e2e7e468c86b"},"\/thricetoss_campion_da_64kb.mp3":{"source":"derivative","creator":"Thomas Campion","title":"Thrice Toss Those Oaken Ashes in the Air - Read by DBL","track":"1","album":"LibriVox Weekly Poetry","genre":"Speech","bitrate":"64","length":"01:05","format":"64Kbps MP3","original":"thricetoss_campion_da.mp3","mtime":"1361123752","size":"523264","md5":"1db714838c687799f41326fad29de906","crc32":"13ffea42","sha1":"6f69a1eefa528ec7fdd184cbd2c373027e6bd842","height":"0","width":"0"},"\/thricetoss_campion_da_esshigh.json.gz":{"source":"derivative","format":"Essentia High GZ","original":"thricetoss_campion_da_esslow.json.gz","mtime":"1420872746","size":"1932","md5":"0a2a49b450e7a4f385470e1d39beba0a","crc32":"b3d8d2da","sha1":"274692fec48d2746d1260eb8380be6a3d4323800"},"\/thricetoss_campion_da_esslow.json.gz":{"source":"derivative","format":"Essentia Low GZ","original":"thricetoss_campion_da.mp3","mtime":"1420872575","size":"21997","md5":"eed0ae0fd4ce181c975b31bd8f664fd7","crc32":"346f5f04","sha1":"78fd7476e2cb30267d26d07fef347a2121e5e3d1"},"\/thricetoss_campion_da_spectrogram.png":{"source":"derivative","format":"Spectrogram","original":"thricetoss_campion_da.mp3","mtime":"1420872542","size":"318125","md5":"5da4c5ad03a04e4efeba739f299682f0","crc32":"8ca1c9ac","sha1":"ccfccea6c02ace6062dade12b0e6ec0055c8a710"},"\/thricetoss_campion_dl.mp3":{"source":"original","format":"128Kbps MP3","creator":"Thomas Campion","album":"LibriVox Weekly Poetry","title":"Thrice Toss Those Oaken Ashes in the Air - Read by DL","length":"62.09","mtime":"1361123702","size":"995630","md5":"90ddd5b6b1da4a97359db44fdcd4db99","crc32":"4e5c2471","sha1":"c52a082d44b573beca82545349bba21dc6b8d7de","artist":"Thomas Campion","track":"2","genre":"Speech","external-identifier":"urn:acoustid:unknown","height":"0","width":"0"},"\/thricetoss_campion_dl.ogg":{"source":"derivative","format":"Ogg Vorbis","original":"thricetoss_campion_dl.mp3","mtime":"1361123781","size":"568290","md5":"d3ff5c859cea6efed520b4766644b989","crc32":"6dd28548","sha1":"a4d7cd123a4ab49cb8e824b34126456033fd3b3d","length":"62.07","height":"0","width":"0"},"\/thricetoss_campion_dl.png":{"source":"derivative","format":"PNG","original":"thricetoss_campion_dl.mp3","mtime":"1420872508","size":"9312","md5":"998e923b1777a69354275616ad3409ca","crc32":"569d7fe1","sha1":"0e881dc5deb4b10f8fd0419a04535c7597ab007a"},"\/thricetoss_campion_dl_64kb.mp3":{"source":"derivative","creator":"Thomas Campion","title":"Thrice Toss Those Oaken Ashes in the Air - Read by DL","track":"2","album":"LibriVox Weekly Poetry","genre":"Speech","bitrate":"64","length":"01:02","format":"64Kbps MP3","original":"thricetoss_campion_dl.mp3","mtime":"1361123744","size":"498176","md5":"27ea0667b87fc20a9addbea4791b43cf","crc32":"005e5f4a","sha1":"6b1b2b1014d8722e2700d7d9f45229976b1c5e26","height":"0","width":"0"},"\/thricetoss_campion_dl_esshigh.json.gz":{"source":"derivative","format":"Essentia High GZ","original":"thricetoss_campion_dl_esslow.json.gz","mtime":"1420872724","size":"1973","md5":"90bb17fd2f2f7c0d176fd3d99b3bba6b","crc32":"721e5e4a","sha1":"f06a173a0a394bdef68bbb16835e31924461be3b"},"\/thricetoss_campion_dl_esslow.json.gz":{"source":"derivative","format":"Essentia Low GZ","original":"thricetoss_campion_dl.mp3","mtime":"1420872626","size":"21517","md5":"8bae991f0a4f9e3d64bcbaa27f580ed4","crc32":"11b966a3","sha1":"7d9fecb707a3ab3f9604d7235fd6712546c61aa9"},"\/thricetoss_campion_dl_spectrogram.png":{"source":"derivative","format":"Spectrogram","original":"thricetoss_campion_dl.mp3","mtime":"1420872539","size":"314596","md5":"256390afa082e06bad8faa2398da401f","crc32":"43d949f8","sha1":"b78b36f99c274b68652c2aceecf24609116162b7"},"\/thricetoss_campion_fs.mp3":{"source":"original","format":"128Kbps MP3","creator":"Thomas Campion","album":"LibriVox Weekly Poetry","title":"Thrice Toss Those Oaken Ashes in the Air - Read by FS","length":"69.07","mtime":"1361123701","size":"1106222","md5":"ca00ddb0bc75386b603fbf6852a37242","crc32":"5a255d1a","sha1":"8f489550472911f70d46ab6a907baf1c8f60f9a5","artist":"Thomas Campion","track":"3","genre":"Speech","external-identifier":"urn:acoustid:unknown","height":"0","width":"0"},"\/thricetoss_campion_fs.ogg":{"source":"derivative","format":"Ogg Vorbis","original":"thricetoss_campion_fs.mp3","mtime":"1361123768","size":"553038","md5":"4eca18a1afb02aab8fb4ffba087f8a6c","crc32":"ed063ae6","sha1":"6b7d7f0f4753de451bd1dfc4750b439dc85441e6","length":"69.04","height":"0","width":"0"},"\/thricetoss_campion_fs.png":{"source":"derivative","format":"PNG","original":"thricetoss_campion_fs.mp3","mtime":"1420872530","size":"10238","md5":"dabdef774e54a5fca0eb49dd5c470746","crc32":"5c498bdc","sha1":"0eaca1a5d3d9d969cc6ebdc5df58f6aea9d06f1a"},"\/thricetoss_campion_fs_64kb.mp3":{"source":"derivative","creator":"Thomas Campion","title":"Thrice Toss Those Oaken Ashes in the Air - Read by FS","track":"3","album":"LibriVox Weekly Poetry","genre":"Speech","bitrate":"64","length":"01:09","format":"64Kbps MP3","original":"thricetoss_campion_fs.mp3","mtime":"1361123746","size":"553984","md5":"8f79098c6b3580d3170bce25310dfe2e","crc32":"9b0a7d17","sha1":"f899380d73d43efcad066e261240b6d27c44bcef","height":"0","width":"0"},"\/thricetoss_campion_fs_esshigh.json.gz":{"source":"derivative","format":"Essentia High GZ","original":"thricetoss_campion_fs_esslow.json.gz","mtime":"1420872718","size":"1974","md5":"e5658bcb9aac3726e36a100b5e47c020","crc32":"8cdba8f3","sha1":"3d9d5ed8a4cb22412a0512802a70195558bdb3fa"},"\/thricetoss_campion_fs_esslow.json.gz":{"source":"derivative","format":"Essentia Low GZ","original":"thricetoss_campion_fs.mp3","mtime":"1420872668","size":"21870","md5":"6d15997d6335f792a0c1b8754ef93ac3","crc32":"db93d868","sha1":"00c7c4a513732daf512dc166823a48af53a69121"},"\/thricetoss_campion_fs_spectrogram.png":{"source":"derivative","format":"Spectrogram","original":"thricetoss_campion_fs.mp3","mtime":"1420872545","size":"227055","md5":"f42456dc0e3d7736d5398d7ba866d19b","crc32":"4c7acbe1","sha1":"e3b179ff3ab7707bb8b01cfa2408a18adfe56632"},"\/thricetoss_campion_gb.mp3":{"source":"original","format":"128Kbps MP3","creator":"Thomas Campion","album":"LibriVox Weekly Poetry","title":"Thrice Toss Those Oaken Ashes in the Air - Read by GB","length":"74.24","mtime":"1361123702","size":"1190016","md5":"4865a7decc03f38515dfa06734affc09","crc32":"15bbe15e","sha1":"da68116a533017ce6270e5d3b5aa0579181d4100","artist":"Thomas Campion","track":"4","genre":"Speech","external-identifier":"urn:acoustid:unknown","height":"0","width":"0"},"\/thricetoss_campion_gb.ogg":{"source":"derivative","format":"Ogg Vorbis","original":"thricetoss_campion_gb.mp3","mtime":"1361123771","size":"707151","md5":"ede1eb8e5322cd1fe94f1efc5414f93d","crc32":"46434c53","sha1":"b991d23d07e2438f7bc30b015f35bbd73717f7a1","length":"74.22","height":"0","width":"0"},"\/thricetoss_campion_gb.png":{"source":"derivative","format":"PNG","original":"thricetoss_campion_gb.mp3","mtime":"1420872527","size":"10245","md5":"9f45a6fcad64759069fdf17b5b24b037","crc32":"9ecc014d","sha1":"7feea70d3e693e5df8467404a0a570d8fa70e964"},"\/thricetoss_campion_gb_64kb.mp3":{"source":"derivative","creator":"Thomas Campion","title":"Thrice Toss Those Oaken Ashes in the Air - Read by GB","track":"4","album":"LibriVox Weekly Poetry","genre":"Speech","bitrate":"64","length":"01:14","format":"64Kbps MP3","original":"thricetoss_campion_gb.mp3","mtime":"1361123741","size":"595456","md5":"900c920131dc940145cc1c3ba6821a22","crc32":"3d8298a5","sha1":"e51d21c91ac4731019cbefb7150b7b661c7c6989","height":"0","width":"0"},"\/thricetoss_campion_gb_esshigh.json.gz":{"source":"derivative","format":"Essentia High GZ","original":"thricetoss_campion_gb_esslow.json.gz","mtime":"1420872729","size":"1934","md5":"36e9864e15b603eb5177adfe78f708b3","crc32":"c9d36657","sha1":"ef95314fd95a29f68d5cea870239b432f5af7e1a"},"\/thricetoss_campion_gb_esslow.json.gz":{"source":"derivative","format":"Essentia Low GZ","original":"thricetoss_campion_gb.mp3","mtime":"1420872592","size":"21698","md5":"3ff3cbec18247d664a4ce5bd44392017","crc32":"e1bf2391","sha1":"73f8d97ea3258e9b5fc25421e3d51ee420186c9e"},"\/thricetoss_campion_gb_spectrogram.png":{"source":"derivative","format":"Spectrogram","original":"thricetoss_campion_gb.mp3","mtime":"1420872541","size":"296488","md5":"0c6553b128d2508135de00af70e77f04","crc32":"e50825f2","sha1":"809a1db90f2e5eb033be9db13d5b4519bd5b71dc"},"\/thricetoss_campion_jab.mp3":{"source":"original","format":"128Kbps MP3","creator":"Thomas Campion","album":"LibriVox Weekly Poetry","title":"Thrice Toss Those Oaken Ashes in the Air - Read by JAB","length":"59.92","mtime":"1361123702","size":"960686","md5":"0cd702d89cfd08fa5c1bbb74f96f88a9","crc32":"67f9b42d","sha1":"e3f91d5194ca5fa4bb841266b2cf80599864107d","artist":"Thomas Campion","track":"5","genre":"Speech","external-identifier":"urn:acoustid:unknown","height":"0","width":"0"},"\/thricetoss_campion_jab.ogg":{"source":"derivative","format":"Ogg Vorbis","original":"thricetoss_campion_jab.mp3","mtime":"1361123774","size":"581383","md5":"bcfd55632e9dfa08bddde5ec54d84870","crc32":"2edaf5fe","sha1":"857621141e0dba76007ee54448810091aad33ccc","length":"59.9","height":"0","width":"0"},"\/thricetoss_campion_jab.png":{"source":"derivative","format":"PNG","original":"thricetoss_campion_jab.mp3","mtime":"1420872533","size":"11403","md5":"ba44a95af7d41bd51385388c29b451dd","crc32":"6ee05555","sha1":"c05fd07723e29757538ce8814c4f22c815420ebc"},"\/thricetoss_campion_jab_64kb.mp3":{"source":"derivative","creator":"Thomas Campion","title":"Thrice Toss Those Oaken Ashes in the Air -Read by JAB","track":"5","album":"LibriVox Weekly Poetry","genre":"Speech","bitrate":"64","length":"01:00","format":"64Kbps MP3","original":"thricetoss_campion_jab.mp3","mtime":"1361123751","size":"481280","md5":"5295b751d07c05dea15161cead7fcc2b","crc32":"0c15f406","sha1":"bd6165d845557204ea3590ecb34da949ff52cc7d","height":"0","width":"0"},"\/thricetoss_campion_jab_esshigh.json.gz":{"source":"derivative","format":"Essentia High GZ","original":"thricetoss_campion_jab_esslow.json.gz","mtime":"1420872735","size":"1981","md5":"b99f76062dbcc2efdbd3122e5da83027","crc32":"05ff6add","sha1":"6ed03df5139f8e4b15b91d241c7897e053f5d2bb"},"\/thricetoss_campion_jab_esslow.json.gz":{"source":"derivative","format":"Essentia Low GZ","original":"thricetoss_campion_jab.mp3","mtime":"1420872641","size":"21514","md5":"36ae61c9d4d33c8b1dc9ed87d6316689","crc32":"848c7764","sha1":"973c26c27044b93203b68e948c3e04522a7ee6b1"},"\/thricetoss_campion_jab_spectrogram.png":{"source":"derivative","format":"Spectrogram","original":"thricetoss_campion_jab.mp3","mtime":"1420872550","size":"319725","md5":"cba9981ced4d5450f20e1b603935e7e6","crc32":"13fcd879","sha1":"b7372c9c0b105eaeaec354b6d94f479417b640b9"},"\/thricetoss_campion_jcm.mp3":{"source":"original","format":"128Kbps MP3","creator":"Thomas Campion","album":"LibriVox Weekly Poetry","title":"Thrice Toss Those Oaken Ashes in the Air - Read by JCM","length":"60.84","mtime":"1361123702","size":"975022","md5":"496f2669ae8eea931563931a13beda13","crc32":"47ab5399","sha1":"b17a08bc172d0c8af85142ee5e332f2b8c67ba97","artist":"Thomas Campion","track":"6","genre":"Speech","external-identifier":"urn:acoustid:unknown","height":"0","width":"0"},"\/thricetoss_campion_jcm.ogg":{"source":"derivative","format":"Ogg Vorbis","original":"thricetoss_campion_jcm.mp3","mtime":"1361123763","size":"533410","md5":"c19be096d7282ba8a21c56e201ed2fbc","crc32":"eec31367","sha1":"9b4b59ba7fc6c292852e36f8ca012fff841a18dd","length":"60.81","height":"0","width":"0"},"\/thricetoss_campion_jcm.png":{"source":"derivative","format":"PNG","original":"thricetoss_campion_jcm.mp3","mtime":"1420872538","size":"9480","md5":"7b6e6d72a9d645360fc3ef6e843ef164","crc32":"c3dad228","sha1":"1aa8366296c6b5dfc377744f31aeebcb8e071629"},"\/thricetoss_campion_jcm_64kb.mp3":{"source":"derivative","creator":"Thomas Campion","title":"Thrice Toss Those Oaken Ashes in the Air - Read by JCM","track":"6","album":"LibriVox Weekly Poetry","genre":"Speech","bitrate":"64","length":"01:00","format":"64Kbps MP3","original":"thricetoss_campion_jcm.mp3","mtime":"1361123749","size":"488448","md5":"0b4301fbef478ea6a496e953778ee950","crc32":"9b982f8b","sha1":"df6205418cfcc3035f50b516be1c1202d8e2d5a0","height":"0","width":"0"},"\/thricetoss_campion_jcm_esshigh.json.gz":{"source":"derivative","format":"Essentia High GZ","original":"thricetoss_campion_jcm_esslow.json.gz","mtime":"1420872741","size":"1966","md5":"41c4cf63eade16b61efbc8099baf14ed","crc32":"153ef828","sha1":"837d9b3c896561f703878decbae18c620095c7b2"},"\/thricetoss_campion_jcm_esslow.json.gz":{"source":"derivative","format":"Essentia Low GZ","original":"thricetoss_campion_jcm.mp3","mtime":"1420872583","size":"21744","md5":"29b617e6b69a5e0431593409240fa3dc","crc32":"36791471","sha1":"3851c57efe96497fd75c3fac2b80125656e8982c"},"\/thricetoss_campion_jcm_spectrogram.png":{"source":"derivative","format":"Spectrogram","original":"thricetoss_campion_jcm.mp3","mtime":"1420872547","size":"280881","md5":"04566b3d453554ddebeac7177c8a8408","crc32":"f4f02c3c","sha1":"303be12c8613e2c6c526685a855a5f4f9525008e"},"\/thricetoss_campion_jm2.mp3":{"source":"original","format":"128Kbps MP3","creator":"Thomas Campion","album":"LibriVox Weekly Poetry","title":"Thrice Toss Those Oaken Ashes in the Air - Read by JM","length":"71.94","mtime":"1361123703","size":"1153326","md5":"07c9179f3ba4a6f3154555f672e8e5a1","crc32":"21bccde2","sha1":"7b66756cb063ce8c70f25658859a49a9078fc734","artist":"Thomas Campion","track":"7","genre":"Speech","external-identifier":"urn:acoustid:unknown","height":"0","width":"0"},"\/thricetoss_campion_jm2.ogg":{"source":"derivative","format":"Ogg Vorbis","original":"thricetoss_campion_jm2.mp3","mtime":"1361123766","size":"633177","md5":"3692e9032ab25b778bc4bbc26ba2c324","crc32":"2f602a3a","sha1":"9a9a74e4fe589a6ca4c69b7172208e3ad8d193e4","length":"71.92","height":"0","width":"0"},"\/thricetoss_campion_jm2.png":{"source":"derivative","format":"PNG","original":"thricetoss_campion_jm2.mp3","mtime":"1420872536","size":"9864","md5":"0e2f16860ffb62f9f804b6a10d874e1b","crc32":"85942ca2","sha1":"2aea3b9662b8c66f343595b498b2236ec89ad990"},"\/thricetoss_campion_jm2_64kb.mp3":{"source":"derivative","creator":"Thomas Campion","title":"Thrice Toss Those Oaken Ashes in the Air - Read by JM","track":"7","album":"LibriVox Weekly Poetry","genre":"Speech","bitrate":"64","length":"01:12","format":"64Kbps MP3","original":"thricetoss_campion_jm2.mp3","mtime":"1361123743","size":"577024","md5":"d441adb7ecfecdba8393e241293a69b4","crc32":"c803e8e0","sha1":"bb3691d980805c15b4354f8945ba0fd4f043e36b","height":"0","width":"0"},"\/thricetoss_campion_jm2_esshigh.json.gz":{"source":"derivative","format":"Essentia High GZ","original":"thricetoss_campion_jm2_esslow.json.gz","mtime":"1420872713","size":"1978","md5":"bc5f2052a9d56f73cde01f19e7e6cac2","crc32":"2d61594d","sha1":"4152343012f4e040a331b63bc2757856268fa9d5"},"\/thricetoss_campion_jm2_esslow.json.gz":{"source":"derivative","format":"Essentia Low GZ","original":"thricetoss_campion_jm2.mp3","mtime":"1420872566","size":"21965","md5":"fc07da10dfd32067cd6a977b27360d16","crc32":"e4a634c4","sha1":"1b3940eed17f40c159eec2ae48c898d432672e3a"},"\/thricetoss_campion_jm2_spectrogram.png":{"source":"derivative","format":"Spectrogram","original":"thricetoss_campion_jm2.mp3","mtime":"1420872553","size":"293656","md5":"97d907e2321f68a3cf64473fb470e1ed","crc32":"6cbdfc41","sha1":"da49ca7c35df75ba31983c01d658c2c4e8bd74a8"},"\/thricetoss_campion_lah.mp3":{"source":"original","format":"128Kbps MP3","creator":"Thomas Campion","album":"LibriVox Weekly Poetry","title":"Thrice Toss Those Oaken Ashes in the Air - Read by LAH","length":"65.07","mtime":"1361123702","size":"1042606","md5":"037fa26bae9fe36340af267d03fe1002","crc32":"03fdc5d3","sha1":"d09d266d580832107d6196c9684c4849cd29fb2e","genre":"Speech","artist":"Thomas Campion","track":"8","external-identifier":"urn:acoustid:unknown","height":"0","width":"0"},"\/thricetoss_campion_lah.ogg":{"source":"derivative","format":"Ogg Vorbis","original":"thricetoss_campion_lah.mp3","mtime":"1361123776","size":"592999","md5":"4965691d3d6330bb6fbbc961f5c2b011","crc32":"e1556205","sha1":"d81d562ad189f45aac505d28892f3805ca98cbb3","length":"65.05","height":"0","width":"0"},"\/thricetoss_campion_lah.png":{"source":"derivative","format":"PNG","original":"thricetoss_campion_lah.mp3","mtime":"1420872504","size":"9965","md5":"86c13d0aa98ee0a2e4b8ae6f12cec848","crc32":"f3994959","sha1":"f7063518647696fbc2eb5f0acc1ee2f7dc5cfceb"},"\/thricetoss_campion_lah_64kb.mp3":{"source":"derivative","creator":"Thomas Campion","title":"Thrice Toss Those Oaken Ashes in the Air - Read by LAH","track":"8","album":"LibriVox Weekly Poetry","genre":"Speech","bitrate":"64","length":"01:05","format":"64Kbps MP3","original":"thricetoss_campion_lah.mp3","mtime":"1361123757","size":"522240","md5":"b8ba1cd9331e8346e00542f3b6a94f83","crc32":"b2435945","sha1":"d5d81f99af7782cf8fc1537d353735c6792e10d3","height":"0","width":"0"},"\/thricetoss_campion_lah_esshigh.json.gz":{"source":"derivative","format":"Essentia High GZ","original":"thricetoss_campion_lah_esslow.json.gz","mtime":"1420872707","size":"1967","md5":"9241ac62c7148382ad93d4a655214a86","crc32":"397ad2cd","sha1":"5e05e247d75538cfa3bd2852e6d2268003eb80ea"},"\/thricetoss_campion_lah_esslow.json.gz":{"source":"derivative","format":"Essentia Low GZ","original":"thricetoss_campion_lah.mp3","mtime":"1420872659","size":"21579","md5":"9b0877444acc992086865f4cec7182e8","crc32":"4fc0c451","sha1":"ecdd5c8a28e084ca203863723c8c7e991d01eb75"},"\/thricetoss_campion_lah_spectrogram.png":{"source":"derivative","format":"Spectrogram","original":"thricetoss_campion_lah.mp3","mtime":"1420872548","size":"297740","md5":"8cf2cf8e8d33b29ca943b13433e6a530","crc32":"5753e85e","sha1":"71e66c474d3bc4ef031ae1da77a5c723b0db8b97"},"\/thricetoss_campion_llw.mp3":{"source":"original","format":"128Kbps MP3","creator":"Thomas Campion","album":"LibriVox Weekly Poetry","title":"Thrice Toss Those Oaken Ashes in the Air - Read by LLW","length":"79.52","mtime":"1361123702","size":"1274158","md5":"afcd2edeb0c1b345305e762556805b44","crc32":"e759bc09","sha1":"c9d97d07521dc3bc9105e3ce8734a1c174d8f9b5","artist":"Thomas Campion","track":"9","genre":"Speech","external-identifier":"urn:acoustid:unknown","height":"0","width":"0"},"\/thricetoss_campion_llw.ogg":{"source":"derivative","format":"Ogg Vorbis","original":"thricetoss_campion_llw.mp3","mtime":"1361123795","size":"716767","md5":"f95d785caf200b169669c36c645686e0","crc32":"0d59953c","sha1":"be26760f503cbcee9f0732c1a1113bf9ca2c73b1","length":"79.49","height":"0","width":"0"},"\/thricetoss_campion_llw.png":{"source":"derivative","format":"PNG","original":"thricetoss_campion_llw.mp3","mtime":"1420872521","size":"8569","md5":"2415969193a69707c0b06890ca7345bd","crc32":"e35b4438","sha1":"9e1302572539fa074efe5a372365f61693fbe759"},"\/thricetoss_campion_llw_64kb.mp3":{"source":"derivative","creator":"Thomas Campion","title":"Thrice Toss Those Oaken Ashes in the Air - Read by LLW","track":"9","album":"LibriVox Weekly Poetry","genre":"Speech","bitrate":"64","length":"01:19","format":"64Kbps MP3","original":"thricetoss_campion_llw.mp3","mtime":"1361123748","size":"637952","md5":"c0cad1452904ae45042ff1b981aea7f0","crc32":"380ca685","sha1":"d030796c0b5b666760c9a3a1a250ac158870923c","height":"0","width":"0"},"\/thricetoss_campion_llw_esshigh.json.gz":{"source":"derivative","format":"Essentia High GZ","original":"thricetoss_campion_llw_esslow.json.gz","mtime":"1420872685","size":"1973","md5":"594829146bcb6ea728a1755d4804bda0","crc32":"081bfa45","sha1":"e44df456fe1088785d34082e8e6e4a14dc6a0301"},"\/thricetoss_campion_llw_esslow.json.gz":{"source":"derivative","format":"Essentia Low GZ","original":"thricetoss_campion_llw.mp3","mtime":"1420872609","size":"22002","md5":"bd6a842afb3e204dd535190aa86b42ac","crc32":"7c151169","sha1":"45bf640f967d6a34e920327aea57fa173cc8d91d"},"\/thricetoss_campion_llw_spectrogram.png":{"source":"derivative","format":"Spectrogram","original":"thricetoss_campion_llw.mp3","mtime":"1420872544","size":"289776","md5":"c4814bd0ed4b191e247480878d3116a2","crc32":"2124ac70","sha1":"e894aa62c15276037f880d2237546d2813cbf293"},"\/thricetoss_campion_mc.mp3":{"source":"original","format":"128Kbps MP3","creator":"Thomas Campion","album":"LibriVox Weekly Poetry","title":"Thrice Toss Those Oaken Ashes in the Air - Read by MC","length":"64.94","mtime":"1361123702","size":"1040558","md5":"314af28bd9e3fb041f4108b07f4af72d","crc32":"46990e51","sha1":"51cba943c3c8eb185d38dfe011d6b424daea89f0","artist":"Thomas Campion","track":"10","genre":"Speech","external-identifier":"urn:acoustid:unknown","height":"0","width":"0"},"\/thricetoss_campion_mc.ogg":{"source":"derivative","format":"Ogg Vorbis","original":"thricetoss_campion_mc.mp3","mtime":"1361123792","size":"607536","md5":"8f23c67f742264d66e133268a6c83427","crc32":"634c215f","sha1":"460970cf290922e77ba034e11e5252d0420d5dac","length":"64.92","height":"0","width":"0"},"\/thricetoss_campion_mc.png":{"source":"derivative","format":"PNG","original":"thricetoss_campion_mc.mp3","mtime":"1420872523","size":"12142","md5":"3a05b0aa87d0f8e60e353b664243f675","crc32":"7405ddd6","sha1":"b6704916ff05d70833cf855731d81d73bddc92c9"},"\/thricetoss_campion_mc_64kb.mp3":{"source":"derivative","creator":"Thomas Campion","title":"Thrice Toss Those Oaken Ashes in the Air - Read by MC","track":"10","album":"LibriVox Weekly Poetry","genre":"Speech","bitrate":"64","length":"01:05","format":"64Kbps MP3","original":"thricetoss_campion_mc.mp3","mtime":"1361123755","size":"521216","md5":"1b4e31dc3d886556b6dd3cadba90f665","crc32":"79ec7ae1","sha1":"d135f77d8f1e5c46c6eca5ad7c2165765375a426","height":"0","width":"0"},"\/thricetoss_campion_mc_esshigh.json.gz":{"source":"derivative","format":"Essentia High GZ","original":"thricetoss_campion_mc_esslow.json.gz","mtime":"1420872680","size":"1936","md5":"29ce66f7e67abdf6ce683c0be82b3611","crc32":"659e53a8","sha1":"f76ca0eaaa91629982e3e39d3a3bc8cdc1a17db5"},"\/thricetoss_campion_mc_esslow.json.gz":{"source":"derivative","format":"Essentia Low GZ","original":"thricetoss_campion_mc.mp3","mtime":"1420872600","size":"21633","md5":"5912e46abf35e24e2625d56a49864229","crc32":"7d5c79b6","sha1":"f92285c2342cdd16d72792c8c82a6d7ae82ff09f"},"\/thricetoss_campion_mc_spectrogram.png":{"source":"derivative","format":"Spectrogram","original":"thricetoss_campion_mc.mp3","mtime":"1420872554","size":"320740","md5":"08c1ae8a3c7fab54db695b148e8e5e66","crc32":"d50bc3e2","sha1":"dedc2d89d6b4a9c5dc7d47c1321ac11f018e2f3f"},"\/thricetoss_campion_rn.mp3":{"source":"original","format":"128Kbps MP3","creator":"Thomas Campion","album":"LibriVox Weekly Poetry","title":"Thrice Toss Those Oaken Ashes in the Air - Read by RN","length":"82.42","mtime":"1361123701","size":"1321262","md5":"4a50374969bebed582902f076e8ef55c","crc32":"45eefb8d","sha1":"0a0a58c9af47d7279dc881eefaab4b5199abb5db","genre":"Speech","artist":"Thomas Campion","track":"11","external-identifier":"urn:acoustid:unknown","height":"0","width":"0"},"\/thricetoss_campion_rn.ogg":{"source":"derivative","format":"Ogg Vorbis","original":"thricetoss_campion_rn.mp3","mtime":"1361123784","size":"760086","md5":"174833b202eaf9eed4f47945b3eb2d2d","crc32":"fbc28f3a","sha1":"1b98b88a833cf0daa74c32a35bff3f6cdd0badc7","length":"82.39","height":"0","width":"0"},"\/thricetoss_campion_rn.png":{"source":"derivative","format":"PNG","original":"thricetoss_campion_rn.mp3","mtime":"1420872515","size":"9600","md5":"151dc329a960c3f6596b618263513788","crc32":"cb067157","sha1":"aae9cd9c398dc93aeeb11bda36be1c36b5cb0355"},"\/thricetoss_campion_rn_64kb.mp3":{"source":"derivative","creator":"Thomas Campion","title":"Thrice Toss Those Oaken Ashes in the Air - Read by RN","track":"11","album":"LibriVox Weekly Poetry","genre":"Speech","bitrate":"64","length":"01:22","format":"64Kbps MP3","original":"thricetoss_campion_rn.mp3","mtime":"1361123760","size":"660992","md5":"9d55cfa6495ee75fb4a4958162be0ea4","crc32":"50cf5192","sha1":"dcefd61f657652ffc3119976c262a2ab3747bb55","height":"0","width":"0"},"\/thricetoss_campion_rn_esshigh.json.gz":{"source":"derivative","format":"Essentia High GZ","original":"thricetoss_campion_rn_esslow.json.gz","mtime":"1420872690","size":"1979","md5":"834cc5ae475b5ba29a13867e3ae1b479","crc32":"5641f301","sha1":"0f011fea588bc7dc01541b7bc76434ec000e8863"},"\/thricetoss_campion_rn_esslow.json.gz":{"source":"derivative","format":"Essentia Low GZ","original":"thricetoss_campion_rn.mp3","mtime":"1420872652","size":"22023","md5":"93eebeeb6413ae03d7f880834a509a1a","crc32":"c64f35da","sha1":"e864be0e934e548ce901f831f8e194ccbc39a478"},"\/thricetoss_campion_rn_spectrogram.png":{"source":"derivative","format":"Spectrogram","original":"thricetoss_campion_rn.mp3","mtime":"1420872551","size":"259013","md5":"e6631f92822a4b7d0cb0cd1c70836ea8","crc32":"73e13040","sha1":"2f2e1c6e0e3fc6b5c6fc1aaa931b7595f4c905bc"},"\/thricetoss_campion_tm.mp3":{"source":"original","format":"128Kbps MP3","creator":"Thomas Campion","album":"LibriVox Weekly Poetry","title":"Thrice Toss Those Oaken Ashes in the Air - Read by TM","length":"72.2","mtime":"1361123701","size":"1157294","md5":"7b08e035a6fc476bbe74a82dbb896d4a","crc32":"e2c83bef","sha1":"d925726812deb0de181694a375f5a4ebd8b632c3","artist":"Thomas Campion","track":"12","genre":"Speech","external-identifier":"urn:acoustid:unknown","height":"0","width":"0"},"\/thricetoss_campion_tm.ogg":{"source":"derivative","format":"Ogg Vorbis","original":"thricetoss_campion_tm.mp3","mtime":"1361123787","size":"664010","md5":"c7fff70a5e7619ff73a8b9c2aff3002c","crc32":"b9f637ed","sha1":"4fa42b52aaa9a81ab2dad5965208ef50fcfbe5ea","length":"72.18","height":"0","width":"0"},"\/thricetoss_campion_tm.png":{"source":"derivative","format":"PNG","original":"thricetoss_campion_tm.mp3","mtime":"1420872518","size":"10395","md5":"3fe0924289daee4c3ce9fd00f57b7c37","crc32":"eea59c7f","sha1":"23ddfac6a7ad8623b36ba901e6afd4953a66369b"},"\/thricetoss_campion_tm_64kb.mp3":{"source":"derivative","creator":"Thomas Campion","title":"Thrice Toss Those Oaken Ashes in the Air - Read by TM","track":"12","album":"LibriVox Weekly Poetry","genre":"Speech","bitrate":"64","length":"01:12","format":"64Kbps MP3","original":"thricetoss_campion_tm.mp3","mtime":"1361123754","size":"579072","md5":"8b125ec8425ae18a26934d0b924c7d45","crc32":"441cb86c","sha1":"56e0a8a995a89b377efa1aa98d12594e6ba8154b","height":"0","width":"0"},"\/thricetoss_campion_tm_esshigh.json.gz":{"source":"derivative","format":"Essentia High GZ","original":"thricetoss_campion_tm_esslow.json.gz","mtime":"1420872696","size":"1963","md5":"82abe6db3f4a093f571fbe93cce1adc8","crc32":"e3b8399c","sha1":"14f9fcf2780d5bfb9b65df0d05c7887b1ff0835c"},"\/thricetoss_campion_tm_esslow.json.gz":{"source":"derivative","format":"Essentia Low GZ","original":"thricetoss_campion_tm.mp3","mtime":"1420872618","size":"22256","md5":"4d4cab8a45d5bb9ef6ab6acb106c4533","crc32":"1102e0dd","sha1":"7f0ab5556887078cac70b77b13f86fbdf80bd5eb"},"\/thricetoss_campion_tm_spectrogram.png":{"source":"derivative","format":"Spectrogram","original":"thricetoss_campion_tm.mp3","mtime":"1420872556","size":"321986","md5":"5c0245aaa2f58eec1f6c15968c5e54a4","crc32":"2ac67cf1","sha1":"02df0924c0be434541402e911d4dc70b98f1113e"},"\/thricetoss_campion_vb.mp3":{"source":"original","format":"128Kbps MP3","creator":"Thomas Campion","album":"LibriVox Weekly Poetry","title":"Thrice Toss Those Oaken Ashes in the Air - Read by VB","length":"61.91","mtime":"1361123701","size":"993454","md5":"fc685092c10ef4ec50a7fca53789880a","crc32":"bf398330","sha1":"fd810ca9128ad6497229cc4a09a8aa2eefcb8369","artist":"Thomas Campion","track":"13","genre":"Speech","external-identifier":"urn:acoustid:unknown","height":"0","width":"0"},"\/thricetoss_campion_vb.ogg":{"source":"derivative","format":"Ogg Vorbis","original":"thricetoss_campion_vb.mp3","mtime":"1361123779","size":"539422","md5":"f883bfd239295833ccb14e2e8986c6aa","crc32":"4a094255","sha1":"f6111151818684f6bbde130626cbc55d926db4f1","length":"61.89","height":"0","width":"0"},"\/thricetoss_campion_vb.png":{"source":"derivative","format":"PNG","original":"thricetoss_campion_vb.mp3","mtime":"1420872511","size":"10724","md5":"f99129addc3bd1961241b05d39e412cb","crc32":"8ff6b13e","sha1":"39de48d6ef4b0fc49291d3d2f88099ac3ac7c4a7"},"\/thricetoss_campion_vb_64kb.mp3":{"source":"derivative","creator":"Thomas Campion","title":"Thrice Toss Those Oaken Ashes in the Air - Read by VB","track":"13","album":"LibriVox Weekly Poetry","genre":"Speech","bitrate":"64","length":"01:01","format":"64Kbps MP3","original":"thricetoss_campion_vb.mp3","mtime":"1361123759","size":"497152","md5":"8ce4ddfa31f60a82c6edbe7176e55883","crc32":"9a808341","sha1":"d10ad9c61c1f89b1a72b823decebb0c62a49c9fc","height":"0","width":"0"},"\/thricetoss_campion_vb_esshigh.json.gz":{"source":"derivative","format":"Essentia High GZ","original":"thricetoss_campion_vb_esslow.json.gz","mtime":"1420872701","size":"1983","md5":"335f285b25083c9ce2c5146fae338061","crc32":"24fedbfb","sha1":"6e7162e62188ba34208ce26c856fd3d68a531b2f"},"\/thricetoss_campion_vb_esslow.json.gz":{"source":"derivative","format":"Essentia Low GZ","original":"thricetoss_campion_vb.mp3","mtime":"1420872633","size":"21590","md5":"1a9c901715340161229c68e7f92b9028","crc32":"821e4566","sha1":"c49075ebb756d826e3ce088f7bfddc3ed53582f7"},"\/thricetoss_campion_vb_spectrogram.png":{"source":"derivative","format":"Spectrogram","original":"thricetoss_campion_vb.mp3","mtime":"1420872557","size":"306812","md5":"7e150cab886ba4770f1ac87d23c730e4","crc32":"9f9eb696","sha1":"f292d7c2ea9930cb33671eae35faf8e4800679ec"}},
"misc":
{"css":"audio","image":"https:\/\/ia902707.us.archive.org\/35\/items\/thricetoss_1302_librivox\/Thrice_Toss_1306_thumb.jpg","header_image":"https:\/\/ia700501.us.archive.org\/1\/items\/librivoxaudio\/librivox.png","collection-title":"The LibriVox Free Audiobook Collection"},
"creativecommons":
{"name":"Public Domain Mark 1.0","license_url":"http:\/\/creativecommons.org\/publicdomain\/mark\/1.0\/","image_url":"http:\/\/i.creativecommons.org\/p\/mark\/1.0\/88x31.png","embed_text":"<?xml version=\"1.0\" encoding=\"utf-8\"?>\n<rdf:RDF\n  xmlns:foaf='http:\/\/xmlns.com\/foaf\/0.1\/'\n  xmlns:cc='http:\/\/creativecommons.org\/ns#'\n  xmlns:rdf='http:\/\/www.w3.org\/1999\/02\/22-rdf-syntax-ns#'\n  xmlns:dc='http:\/\/purl.org\/dc\/elements\/1.1\/'\n  xmlns:dcq='http:\/\/purl.org\/dc\/terms\/'\n>\n  <cc:License rdf:about=\"http:\/\/creativecommons.org\/publicdomain\/mark\/1.0\/\">\n    <cc:permits rdf:resource=\"http:\/\/creativecommons.org\/ns#Reproduction\"\/>\n    <cc:permits rdf:resource=\"http:\/\/creativecommons.org\/ns#DerivativeWorks\"\/>\n    <cc:permits rdf:resource=\"http:\/\/creativecommons.org\/ns#Distribution\"\/>\n    <dc:identifier>mark<\/dc:identifier>\n    <dcq:hasVersion>1.0<\/dcq:hasVersion>\n    <foaf:logo rdf:resource=\"http:\/\/i.creativecommons.org\/p\/mark\/1.0\/80x15.png\"\/>\n    <foaf:logo rdf:resource=\"http:\/\/i.creativecommons.org\/p\/mark\/1.0\/88x31.png\"\/>\n    <cc:licenseClass rdf:resource=\"http:\/\/creativecommons.org\/license\/publicdomain\/\"\/>\n    <dc:title xml:lang=\"be\">Public Domain Mark 1.0<\/dc:title>\n    <dc:title xml:lang=\"bn\">Public Domain Mark 1.0<\/dc:title>\n    <dc:title xml:lang=\"ast-es\">Public Domain Mark 1.0<\/dc:title>\n    <dc:title xml:lang=\"en-ca\">Public Domain Mark 1.0<\/dc:title>\n    <dc:title xml:lang=\"bg\">Public Domain Mark 1.0<\/dc:title>\n    <dc:title xml:lang=\"cs\">Public Domain Mark 1.0<\/dc:title>\n    <dc:title xml:lang=\"ar\">Public Domain Mark 1.0<\/dc:title>\n    <dc:title xml:lang=\"eo\">Public Domain Mark 1.0<\/dc:title>\n    <dc:title xml:lang=\"fi\">Public Domain Mark 1.0<\/dc:title>\n    <dc:title xml:lang=\"it\">Public Domain Mark 1.0<\/dc:title>\n    <dc:title xml:lang=\"sv\">Public Domain Mark 1.0<\/dc:title>\n    <dc:title xml:lang=\"sl\">Public Domain Mark 1.0<\/dc:title>\n    <dc:title xml:lang=\"de-ch\">Public Domain Mark 1.0<\/dc:title>\n    <dc:title xml:lang=\"da\">Public Domain Mark 1.0<\/dc:title>\n    <dc:title xml:lang=\"en-hk\">Public Domain Mark 1.0<\/dc:title>\n    <dc:title xml:lang=\"i18n\">${licenses.publicdomain_mark_title} 1.0<\/dc:title>\n    <dc:title xml:lang=\"en\">Public Domain Mark 1.0<\/dc:title>\n    <dc:title xml:lang=\"mk\">Public Domain Mark 1.0<\/dc:title>\n    <dc:title xml:lang=\"it-ch\">Public Domain Mark 1.0<\/dc:title>\n    <dc:title xml:lang=\"fr-ch\">Public Domain Mark 1.0<\/dc:title>\n    <dc:title xml:lang=\"nl\">Public Domain Mark 1.0<\/dc:title>\n    <dc:title xml:lang=\"eu\">Public Domain Mark 1.0<\/dc:title>\n    <dc:title xml:lang=\"hy\">Public Domain Mark 1.0<\/dc:title>\n    <dc:title xml:lang=\"el\">Public Domain Mark 1.0<\/dc:title>\n    <dc:title xml:lang=\"vi\">Public Domain Mark 1.0<\/dc:title>\n    <dc:title xml:lang=\"es-pr\">Public Domain Mark 1.0<\/dc:title>\n    <dc:title xml:lang=\"id\">Public Domain Mark 1.0<\/dc:title>\n    <dc:title xml:lang=\"he\">Public Domain Mark 1.0<\/dc:title>\n    <dc:title xml:lang=\"lv\">Public Domain Mark 1.0<\/dc:title>\n    <dc:title xml:lang=\"lt\">Public Domain Mark 1.0<\/dc:title>\n    <dc:title xml:lang=\"oci-es\">Public Domain Mark 1.0<\/dc:title>\n    <dc:title xml:lang=\"th\">Public Domain Mark 1.0<\/dc:title>\n    <dc:title xml:lang=\"sr-latn\">Public Domain Mark 1.0<\/dc:title>\n    <dc:title xml:lang=\"ta\">Public Domain Mark 1.0<\/dc:title>\n    <dc:title xml:lang=\"es-ec\">Public Domain Mark 1.0<\/dc:title>\n    <dc:title xml:lang=\"zh-tw\">Public Domain Mark 1.0<\/dc:title>\n    <dc:title xml:lang=\"az\">Public Domain Mark 1.0<\/dc:title>\n    <dc:title xml:lang=\"es-pe\">Public Domain Mark 1.0<\/dc:title>\n    <dc:title xml:lang=\"pt-br\">Public Domain Mark 1.0<\/dc:title>\n    <dc:title xml:lang=\"es-co\">Public Domain Mark 1.0<\/dc:title>\n    <dc:title xml:lang=\"no\">Public Domain Mark 1.0<\/dc:title>\n    <dc:title xml:lang=\"es-gt\">Public Domain Mark 1.0<\/dc:title>\n    <dc:title xml:lang=\"es-cl\">Public Domain Mark 1.0<\/dc:title>\n    <dc:title xml:lang=\"ur\">Public Domain Mark 1.0<\/dc:title>\n    <dc:title xml:lang=\"de\">Public Domain Mark 1.0<\/dc:title>\n    <dc:title xml:lang=\"hu\">Public Domain Mark 1.0<\/dc:title>\n    <dc:title xml:lang=\"es\">Public Domain Mark 1.0<\/dc:title>\n    <dc:title xml:lang=\"fr-lu\">Public Domain Mark 1.0<\/dc:title>\n    <dc:title xml:lang=\"hr\">Public Domain Mark 1.0<\/dc:title>\n    <dc:title xml:lang=\"as\">Public Domain Mark 1.0<\/dc:title>\n    <dc:title xml:lang=\"en-sg\">Public Domain Mark 1.0<\/dc:title>\n    <dc:title xml:lang=\"zh-hk\">Public Domain Mark 1.0<\/dc:title>\n    <dc:title xml:lang=\"en-gb\">Public Domain Mark 1.0<\/dc:title>\n    <dc:title xml:lang=\"es-ar\">Public Domain Mark 1.0<\/dc:title>\n    <dc:title xml:lang=\"zu\">Public Domain Mark 1.0<\/dc:title>\n    <dc:title xml:lang=\"de-at\">Public Domain Mark 1.0<\/dc:title>\n    <dc:title xml:lang=\"ca\">Public Domain Mark 1.0<\/dc:title>\n    <dc:title xml:lang=\"pt-pt\">Public Domain Mark 1.0<\/dc:title>\n    <dc:title xml:lang=\"ms\">Public Domain Mark 1.0<\/dc:title>\n    <dc:title xml:lang=\"pt\">Public Domain Mark 1.0<\/dc:title>\n    <dc:title xml:lang=\"pl\">Public Domain Mark 1.0<\/dc:title>\n    <dc:title xml:lang=\"ga\">Public Domain Mark 1.0<\/dc:title>\n    <dc:title xml:lang=\"es-mx\">Public Domain Mark 1.0<\/dc:title>\n    <dc:title xml:lang=\"zh\">Public Domain Mark 1.0<\/dc:title>\n    <dc:title xml:lang=\"gl\">Public Domain Mark 1.0<\/dc:title>\n    <dc:title xml:lang=\"fr-ca\">Public Domain Mark 1.0<\/dc:title>\n    <dc:title xml:lang=\"tr\">Public Domain Mark 1.0<\/dc:title>\n    <dc:title xml:lang=\"en-us\">Public Domain Mark 1.0<\/dc:title>\n    <dc:title xml:lang=\"ru\">Public Domain Mark 1.0<\/dc:title>\n    <dc:title xml:lang=\"is\">Public Domain Mark 1.0<\/dc:title>\n    <dc:title xml:lang=\"af\">Public Domain Mark 1.0<\/dc:title>\n    <dc:title xml:lang=\"uk\">Public Domain Mark 1.0<\/dc:title>\n    <dc:title xml:lang=\"hi\">Public Domain Mark 1.0<\/dc:title>\n    <dc:title xml:lang=\"nso\">Public Domain Mark 1.0<\/dc:title>\n    <dc:title xml:lang=\"sr\">Public Domain Mark 1.0<\/dc:title>\n    <dc:title xml:lang=\"ro\">Public Domain Mark 1.0<\/dc:title>\n    <dc:title xml:lang=\"ko\">Public Domain Mark 1.0<\/dc:title>\n    <dc:title xml:lang=\"mn\">Public Domain Mark 1.0<\/dc:title>\n    <dc:title xml:lang=\"fr\">Public Domain Mark 1.0<\/dc:title>\n    <dc:title xml:lang=\"ja\">Public Domain Mark 1.0<\/dc:title>\n  <\/cc:License>\n<\/rdf:RDF>"},
"item":
{"downloads":448,"week":3,"month":8}}